[{"id":"1f5ef3b4-ca92-479e-b251-2c876eee40d2","is_verified":false,"reviewed_at":null,"rejected_info":"dog apple dog moon random orange sun happy dog orange","user_id":"436660d3-98b4-45d9-98c8-098c603a442b","request_date":"2024-01-09T21:06:52.883Z","front_identity_card_image_link":"https://picsum.photos/200/300?random=502309983","back_identity_card_image_link":"https://picsum.photos/200/300?random=409689149","portrait_image_link":"https://picsum.photos/200/300?random=489088128","full_name":"happy dog banana random random cat sun moon orange happy","sex":false,"dob":"1994-07-26T17:57:09.855Z","identity_card_no":"123456789102","identity_card_issued_date":"2019-08-27T05:43:28.641Z","issued_by":"Công an Hà Nội"},{"id":"a81146b2-cf9c-48d0-aef2-863c0acc29bc","is_verified":false,"reviewed_at":null,"rejected_info":"apple happy banana orange dog banana cat moon banana orange","user_id":"891d88a3-3f3b-45d7-9bea-55398aa02b06","request_date":"2024-01-09T21:06:52.884Z","front_identity_card_image_link":"https://picsum.photos/200/300?random=215396447","back_identity_card_image_link":"https://picsum.photos/200/300?random=439255240","portrait_image_link":"https://picsum.photos/200/300?random=549910759","full_name":"banana cat moon cat banana banana orange sad apple dog","sex":false,"dob":"2001-03-12T10:40:55.835Z","identity_card_no":"123456789103","identity_card_issued_date":"2017-12-06T18:12:49.213Z","issued_by":"Công an Hà Nội"},{"id":"9d5175f0-fcb1-47c7-a0ec-421226a2e37f","is_verified":false,"reviewed_at":null,"rejected_info":"random apple orange moon happy sun orange happy sad random","user_id":"5ebc825b-48dc-4b33-910d-a711999934c4","request_date":"2024-01-09T21:06:52.884Z","front_identity_card_image_link":"https://picsum.photos/200/300?random=697470730","back_identity_card_image_link":"https://picsum.photos/200/300?random=453348422","portrait_image_link":"https://picsum.photos/200/300?random=843445786","full_name":"sun apple random orange cat banana sad cat cat sad","sex":true,"dob":"2006-10-26T09:13:07.605Z","identity_card_no":"123456789104","identity_card_issued_date":"2016-05-23T22:11:57.437Z","issued_by":"Công an Hà Nội"},{"id":"44fd2f35-6fff-43c9-a015-393c3eb87fbb","is_verified":false,"reviewed_at":null,"rejected_info":"sad sad cat apple banana cat banana dog cat random","user_id":"b9776123-9188-4e95-995d-44311cfe7445","request_date":"2024-01-09T21:06:52.884Z","front_identity_card_image_link":"https://picsum.photos/200/300?random=23535553","back_identity_card_image_link":"https://picsum.photos/200/300?random=262850130","portrait_image_link":"https://picsum.photos/200/300?random=313381205","full_name":"sad sun banana orange sun banana dog orange happy sun","sex":false,"dob":"1971-02-28T09:00:25.175Z","identity_card_no":"123456789105","identity_card_issued_date":"2012-06-08T10:07:14.789Z","issued_by":"Công an Hà Nội"},{"id":"4ba8d138-6105-4814-98bc-bef9285c70fd","is_verified":false,"reviewed_at":null,"rejected_info":"dog dog sad sad orange orange banana moon sun sad","user_id":"5ebc825b-48dc-4b33-910d-a711999934c4","request_date":"2024-01-09T21:06:52.884Z","front_identity_card_image_link":"https://picsum.photos/200/300?random=316778311","back_identity_card_image_link":"https://picsum.photos/200/300?random=603105796","portrait_image_link":"https://picsum.photos/200/300?random=730805449","full_name":"apple orange apple orange sun dog sun apple sad happy","sex":true,"dob":"2023-12-13T14:21:48.014Z","identity_card_no":"123456789106","identity_card_issued_date":"2011-12-30T02:49:32.938Z","issued_by":"Công an Hà Nội"},{"id":"c952ef59-f102-4245-9cd9-bd7f86b2238a","is_verified":true,"reviewed_at":"2024-01-09T21:06:52.884Z","rejected_info":null,"user_id":"28223664-4747-424e-b2e3-27ace26bc553","request_date":"2024-01-09T21:06:52.884Z","front_identity_card_image_link":"https://picsum.photos/200/300?random=93823531","back_identity_card_image_link":"https://picsum.photos/200/300?random=676886866","portrait_image_link":"https://picsum.photos/200/300?random=906720801","full_name":"random random happy random happy dog random dog random moon","sex":false,"dob":"2012-04-10T04:06:18.318Z","identity_card_no":"123456789107","identity_card_issued_date":"2014-05-01T05:17:22.097Z","issued_by":"Công an Hà Nội"},{"id":"936cb14a-3210-4ad4-9032-4d7dae4e59fe","is_verified":false,"reviewed_at":null,"rejected_info":"dog apple moon moon orange cat banana banana banana banana","user_id":"1a9a5785-721a-4bb5-beb7-9d752e2070d4","request_date":"2024-01-09T21:06:52.884Z","front_identity_card_image_link":"https://picsum.photos/200/300?random=95429552","back_identity_card_image_link":"https://picsum.photos/200/300?random=593151532","portrait_image_link":"https://picsum.photos/200/300?random=4015631","full_name":"orange sad sad orange dog banana orange banana sun cat","sex":true,"dob":"2008-11-01T17:41:20.359Z","identity_card_no":"123456789108","identity_card_issued_date":"2022-06-06T09:35:56.351Z","issued_by":"Công an Hà Nội"},{"id":"18527649-dd8f-4ba9-a6b7-3af0df0b4214","is_verified":false,"reviewed_at":null,"rejected_info":"random happy apple sun random sun sun random happy sad","user_id":"eb9c2609-0dc7-426b-9347-d59795d517a9","request_date":"2024-01-09T21:06:52.884Z","front_identity_card_image_link":"https://picsum.photos/200/300?random=825973734","back_identity_card_image_link":"https://picsum.photos/200/300?random=550720879","portrait_image_link":"https://picsum.photos/200/300?random=44394533","full_name":"happy cat orange random banana orange sun apple banana sun","sex":true,"dob":"1996-02-10T04:01:41.337Z","identity_card_no":"123456789109","identity_card_issued_date":"2011-05-21T18:18:45.759Z","issued_by":"Công an Hà Nội"},{"id":"81019e30-5290-40eb-adf8-077a33b9e1d6","is_verified":false,"reviewed_at":null,"rejected_info":"random happy sun sun random happy sad happy cat happy","user_id":"eb9c2609-0dc7-426b-9347-d59795d517a9","request_date":"2024-01-09T21:06:52.884Z","front_identity_card_image_link":"https://picsum.photos/200/300?random=556186713","back_identity_card_image_link":"https://picsum.photos/200/300?random=111481567","portrait_image_link":"https://picsum.photos/200/300?random=308272583","full_name":"dog moon moon random sun moon dog sun sad sad","sex":false,"dob":"1981-05-25T18:58:17.094Z","identity_card_no":"123456789110","identity_card_issued_date":"2016-10-07T02:01:24.393Z","issued_by":"Công an Hà Nội"},{"id":"532e7baa-2d1a-4af6-b888-7de30ddaff70","is_verified":false,"reviewed_at":null,"rejected_info":"banana happy orange dog cat apple orange random dog orange","user_id":"8f021f08-c21e-4d5b-8880-bd8954f37e45","request_date":"2024-01-09T21:06:52.884Z","front_identity_card_image_link":"https://picsum.photos/200/300?random=533662397","back_identity_card_image_link":"https://picsum.photos/200/300?random=416454990","portrait_image_link":"https://picsum.photos/200/300?random=71410589","full_name":"sad sun orange dog sad cat moon random cat apple","sex":false,"dob":"1989-04-01T14:59:15.313Z","identity_card_no":"123456789111","identity_card_issued_date":"2001-09-09T18:13:57.748Z","issued_by":"Công an Hà Nội"},{"id":"e1beca20-a9fb-4ebd-aa86-d3c436b35340","is_verified":false,"reviewed_at":null,"rejected_info":"sad cat happy orange cat banana banana random random sun","user_id":"5ebc825b-48dc-4b33-910d-a711999934c4","request_date":"2024-01-09T21:06:52.884Z","front_identity_card_image_link":"https://picsum.photos/200/300?random=84011722","back_identity_card_image_link":"https://picsum.photos/200/300?random=605772143","portrait_image_link":"https://picsum.photos/200/300?random=78156066","full_name":"orange cat random banana cat cat apple sun moon orange","sex":false,"dob":"2019-01-16T13:25:27.720Z","identity_card_no":"123456789112","identity_card_issued_date":"2009-01-25T14:56:05.022Z","issued_by":"Công an Hà Nội"},{"id":"9068975f-1478-4884-a854-caf7f87b4afd","is_verified":false,"reviewed_at":null,"rejected_info":"banana random sad moon cat cat random sad banana random","user_id":"436660d3-98b4-45d9-98c8-098c603a442b","request_date":"2024-01-09T21:06:52.884Z","front_identity_card_image_link":"https://picsum.photos/200/300?random=743349348","back_identity_card_image_link":"https://picsum.photos/200/300?random=840848389","portrait_image_link":"https://picsum.photos/200/300?random=56220222","full_name":"cat banana cat happy moon random cat random random orange","sex":true,"dob":"2015-01-12T04:23:00.271Z","identity_card_no":"123456789113","identity_card_issued_date":"2002-12-29T07:50:23.017Z","issued_by":"Công an Hà Nội"},{"id":"47769ebc-d961-418a-8d7a-155fbc780ccf","is_verified":true,"reviewed_at":"2024-01-09T21:06:52.884Z","rejected_info":null,"user_id":"cda34506-be46-4dcb-94f3-e92cf8868222","request_date":"2024-01-09T21:06:52.884Z","front_identity_card_image_link":"https://picsum.photos/200/300?random=312808486","back_identity_card_image_link":"https://picsum.photos/200/300?random=796871650","portrait_image_link":"https://picsum.photos/200/300?random=971342133","full_name":"random random banana happy moon dog random dog random banana","sex":false,"dob":"2010-03-14T14:57:27.065Z","identity_card_no":"123456789114","identity_card_issued_date":"2005-12-15T05:20:13.316Z","issued_by":"Công an Hà Nội"},{"id":"c0ed222e-fd1c-443d-9fb3-8295139c3411","is_verified":false,"reviewed_at":null,"rejected_info":"cat moon apple sad moon apple moon random random sun","user_id":"acd91d26-4e9c-4807-94b7-57015dd554b8","request_date":"2024-01-09T21:06:52.884Z","front_identity_card_image_link":"https://picsum.photos/200/300?random=794903841","back_identity_card_image_link":"https://picsum.photos/200/300?random=869979692","portrait_image_link":"https://picsum.photos/200/300?random=728195987","full_name":"moon moon orange sun apple banana banana apple dog random","sex":true,"dob":"2010-07-06T08:40:40.076Z","identity_card_no":"123456789115","identity_card_issued_date":"2002-01-11T05:26:11.807Z","issued_by":"Công an Hà Nội"},{"id":"3c76b7fc-385e-45ba-899b-6470313d07fc","is_verified":false,"reviewed_at":null,"rejected_info":"orange orange moon sad apple cat banana banana apple cat","user_id":"8bc42aed-0036-45a2-8e1d-8041afe12d23","request_date":"2024-01-09T21:06:52.884Z","front_identity_card_image_link":"https://picsum.photos/200/300?random=209662951","back_identity_card_image_link":"https://picsum.photos/200/300?random=524786630","portrait_image_link":"https://picsum.photos/200/300?random=900202910","full_name":"cat cat banana dog apple cat banana sun sad moon","sex":true,"dob":"1976-05-19T17:54:49.762Z","identity_card_no":"123456789116","identity_card_issued_date":"2014-02-01T01:29:46.398Z","issued_by":"Công an Hà Nội"},{"id":"aa6cb58b-3152-498b-8ed4-d1c6228e4c92","is_verified":false,"reviewed_at":null,"rejected_info":"moon sun random happy sun banana sad random orange moon","user_id":"1a9a5785-721a-4bb5-beb7-9d752e2070d4","request_date":"2024-01-09T21:06:52.884Z","front_identity_card_image_link":"https://picsum.photos/200/300?random=47016850","back_identity_card_image_link":"https://picsum.photos/200/300?random=473645668","portrait_image_link":"https://picsum.photos/200/300?random=756642903","full_name":"happy cat sad moon banana moon happy banana sun cat","sex":true,"dob":"1981-02-27T08:08:15.318Z","identity_card_no":"123456789117","identity_card_issued_date":"2008-04-06T16:29:25.182Z","issued_by":"Công an Hà Nội"},{"id":"c0a0a75a-9623-402e-bad3-bc6633b81e0b","is_verified":false,"reviewed_at":null,"rejected_info":"banana orange banana sun sun happy apple orange cat cat","user_id":"8bc42aed-0036-45a2-8e1d-8041afe12d23","request_date":"2024-01-09T21:06:52.884Z","front_identity_card_image_link":"https://picsum.photos/200/300?random=522227481","back_identity_card_image_link":"https://picsum.photos/200/300?random=507354912","portrait_image_link":"https://picsum.photos/200/300?random=708041393","full_name":"sun sad orange happy orange orange orange sad apple happy","sex":true,"dob":"2007-05-29T07:58:45.755Z","identity_card_no":"123456789118","identity_card_issued_date":"2003-05-26T22:37:48.957Z","issued_by":"Công an Hà Nội"},{"id":"677ee3cd-662f-4b9c-9b45-415516cc6f04","is_verified":false,"reviewed_at":null,"rejected_info":"apple apple dog orange apple happy random happy sun sad","user_id":"28223664-4747-424e-b2e3-27ace26bc553","request_date":"2024-01-09T21:06:52.885Z","front_identity_card_image_link":"https://picsum.photos/200/300?random=75608778","back_identity_card_image_link":"https://picsum.photos/200/300?random=163056239","portrait_image_link":"https://picsum.photos/200/300?random=312495048","full_name":"sad sad sun orange happy banana random random happy random","sex":false,"dob":"2003-02-27T07:52:12.978Z","identity_card_no":"123456789119","identity_card_issued_date":"2019-11-14T01:13:05.856Z","issued_by":"Công an Hà Nội"},{"id":"eb83035a-993e-4683-8992-b2492efe6df4","is_verified":false,"reviewed_at":null,"rejected_info":"sad banana random apple orange orange sun dog happy sun","user_id":"280d8b28-07ae-43e7-a54e-6468b6acf519","request_date":"2024-01-09T21:06:52.885Z","front_identity_card_image_link":"https://picsum.photos/200/300?random=777962076","back_identity_card_image_link":"https://picsum.photos/200/300?random=295707835","portrait_image_link":"https://picsum.photos/200/300?random=772465740","full_name":"random happy orange apple sun banana banana random cat sad","sex":true,"dob":"2002-11-16T14:14:01.747Z","identity_card_no":"123456789120","identity_card_issued_date":"2021-01-25T11:46:29.387Z","issued_by":"Công an Hà Nội"},{"id":"6eb83f0f-b546-4f20-924b-7f36d6ffaabd","is_verified":false,"reviewed_at":null,"rejected_info":"banana banana cat banana orange random cat happy cat apple","user_id":"5ebc825b-48dc-4b33-910d-a711999934c4","request_date":"2024-01-09T21:06:52.885Z","front_identity_card_image_link":"https://picsum.photos/200/300?random=238763968","back_identity_card_image_link":"https://picsum.photos/200/300?random=133275751","portrait_image_link":"https://picsum.photos/200/300?random=175066138","full_name":"cat apple orange random sad random happy happy happy dog","sex":true,"dob":"1979-01-26T22:30:10.177Z","identity_card_no":"123456789121","identity_card_issued_date":"2007-11-07T16:08:20.410Z","issued_by":"Công an Hà Nội"},{"id":"b32b6caa-277b-4a2b-8ca1-1cef9c634592","is_verified":false,"reviewed_at":null,"rejected_info":"happy sad cat sun cat happy sad orange sad sad","user_id":"1a9a5785-721a-4bb5-beb7-9d752e2070d4","request_date":"2024-01-09T21:06:52.885Z","front_identity_card_image_link":"https://picsum.photos/200/300?random=156225101","back_identity_card_image_link":"https://picsum.photos/200/300?random=683246177","portrait_image_link":"https://picsum.photos/200/300?random=94041057","full_name":"moon happy happy orange random apple orange cat cat moon","sex":false,"dob":"1973-11-29T09:38:50.246Z","identity_card_no":"123456789122","identity_card_issued_date":"2005-02-04T09:52:01.152Z","issued_by":"Công an Hà Nội"},{"id":"d76fc8e3-e251-43ee-8ee8-a5d6332d5aa8","is_verified":false,"reviewed_at":null,"rejected_info":"moon random dog sun apple happy sad happy apple random","user_id":"a9eb0d7d-025b-48fa-9ff7-b792b249c159","request_date":"2024-01-09T21:06:52.885Z","front_identity_card_image_link":"https://picsum.photos/200/300?random=204400276","back_identity_card_image_link":"https://picsum.photos/200/300?random=550074373","portrait_image_link":"https://picsum.photos/200/300?random=875998300","full_name":"sad sad dog dog orange sad apple moon orange happy","sex":true,"dob":"1986-04-23T17:46:04.142Z","identity_card_no":"123456789123","identity_card_issued_date":"2023-04-03T03:22:39.680Z","issued_by":"Công an Hà Nội"},{"id":"3da6141f-5c5a-42e3-96e6-6b446abfb946","is_verified":false,"reviewed_at":null,"rejected_info":"apple moon banana sad sad banana sun dog moon happy","user_id":"8f021f08-c21e-4d5b-8880-bd8954f37e45","request_date":"2024-01-09T21:06:52.885Z","front_identity_card_image_link":"https://picsum.photos/200/300?random=904699625","back_identity_card_image_link":"https://picsum.photos/200/300?random=122327235","portrait_image_link":"https://picsum.photos/200/300?random=246086094","full_name":"happy moon moon sun cat random banana random orange banana","sex":true,"dob":"2015-10-22T12:47:45.280Z","identity_card_no":"123456789124","identity_card_issued_date":"2001-07-25T12:23:47.223Z","issued_by":"Công an Hà Nội"},{"id":"44f90ea6-a200-4389-9b33-5abc5cf8123f","is_verified":false,"reviewed_at":null,"rejected_info":"happy dog dog orange happy random cat apple sad cat","user_id":"d45afc3e-05e0-41a7-b38d-7e801bf92f04","request_date":"2024-01-09T21:06:52.885Z","front_identity_card_image_link":"https://picsum.photos/200/300?random=435393330","back_identity_card_image_link":"https://picsum.photos/200/300?random=466069988","portrait_image_link":"https://picsum.photos/200/300?random=264795346","full_name":"dog sad cat moon orange orange dog sun banana sun","sex":false,"dob":"2018-09-25T15:10:11.706Z","identity_card_no":"123456789125","identity_card_issued_date":"2018-09-20T22:35:36.797Z","issued_by":"Công an Hà Nội"},{"id":"bce9209e-89e9-4eb2-a160-a35c0b229e0b","is_verified":false,"reviewed_at":null,"rejected_info":"cat happy random cat sad cat sad cat dog cat","user_id":"acd91d26-4e9c-4807-94b7-57015dd554b8","request_date":"2024-01-09T21:06:52.885Z","front_identity_card_image_link":"https://picsum.photos/200/300?random=59096484","back_identity_card_image_link":"https://picsum.photos/200/300?random=794102629","portrait_image_link":"https://picsum.photos/200/300?random=42768336","full_name":"banana random sun sad happy happy random random random moon","sex":true,"dob":"2014-01-27T20:32:31.866Z","identity_card_no":"123456789126","identity_card_issued_date":"2017-11-18T15:43:47.803Z","issued_by":"Công an Hà Nội"},{"id":"e8086b93-dbb3-4a7b-82da-56a6cd467703","is_verified":false,"reviewed_at":null,"rejected_info":"cat moon orange apple banana orange sun random apple sun","user_id":"8bc42aed-0036-45a2-8e1d-8041afe12d23","request_date":"2024-01-09T21:06:52.885Z","front_identity_card_image_link":"https://picsum.photos/200/300?random=255309078","back_identity_card_image_link":"https://picsum.photos/200/300?random=194706794","portrait_image_link":"https://picsum.photos/200/300?random=724549030","full_name":"banana banana sad dog sun banana sad random apple moon","sex":true,"dob":"1997-01-15T22:04:28.589Z","identity_card_no":"123456789127","identity_card_issued_date":"2023-03-31T05:50:57.415Z","issued_by":"Công an Hà Nội"},{"id":"01e64fa6-b018-47e5-a2f6-d88189493fed","is_verified":false,"reviewed_at":null,"rejected_info":"apple sun moon sun sad sun apple cat dog happy","user_id":"032eb0aa-df19-4e4c-9b10-19ede9606f91","request_date":"2024-01-09T21:06:52.885Z","front_identity_card_image_link":"https://picsum.photos/200/300?random=68777150","back_identity_card_image_link":"https://picsum.photos/200/300?random=556139271","portrait_image_link":"https://picsum.photos/200/300?random=305663207","full_name":"apple sun random orange random sad orange random random apple","sex":false,"dob":"1982-07-15T05:36:13.192Z","identity_card_no":"123456789128","identity_card_issued_date":"2012-08-06T08:48:48.685Z","issued_by":"Công an Hà Nội"},{"id":"8252b730-ad61-41e7-9adb-af1bc9bd1430","is_verified":false,"reviewed_at":null,"rejected_info":"dog random cat random banana sad cat happy apple orange","user_id":"346ce7ff-9c1e-43f5-8450-1296ece15692","request_date":"2024-01-09T21:06:52.885Z","front_identity_card_image_link":"https://picsum.photos/200/300?random=223953060","back_identity_card_image_link":"https://picsum.photos/200/300?random=6953773","portrait_image_link":"https://picsum.photos/200/300?random=140542878","full_name":"sun orange orange random orange cat dog sun banana happy","sex":false,"dob":"1987-10-26T21:53:02.886Z","identity_card_no":"123456789129","identity_card_issued_date":"2022-05-20T20:54:27.061Z","issued_by":"Công an Hà Nội"},{"id":"1e3c25d8-70a7-4bb1-a646-952273ca5159","is_verified":false,"reviewed_at":null,"rejected_info":"sun dog sun cat banana happy moon orange dog apple","user_id":"032eb0aa-df19-4e4c-9b10-19ede9606f91","request_date":"2024-01-09T21:06:52.885Z","front_identity_card_image_link":"https://picsum.photos/200/300?random=142665676","back_identity_card_image_link":"https://picsum.photos/200/300?random=368892132","portrait_image_link":"https://picsum.photos/200/300?random=523742913","full_name":"apple orange cat orange moon moon sad apple random moon","sex":true,"dob":"2010-09-30T02:45:55.542Z","identity_card_no":"123456789130","identity_card_issued_date":"2015-09-02T21:29:42.555Z","issued_by":"Công an Hà Nội"},{"id":"b0e43e7f-26ec-4c48-a3e3-4a6e0e489d7c","is_verified":false,"reviewed_at":null,"rejected_info":"cat banana random dog sad sun moon moon banana orange","user_id":"b9776123-9188-4e95-995d-44311cfe7445","request_date":"2024-01-09T21:06:52.885Z","front_identity_card_image_link":"https://picsum.photos/200/300?random=230983044","back_identity_card_image_link":"https://picsum.photos/200/300?random=826513749","portrait_image_link":"https://picsum.photos/200/300?random=424106421","full_name":"banana happy apple random dog cat sun apple cat cat","sex":false,"dob":"1977-07-20T15:39:09.518Z","identity_card_no":"123456789131","identity_card_issued_date":"2005-07-19T15:05:11.983Z","issued_by":"Công an Hà Nội"},{"id":"f66d3a06-8299-4a7b-8644-b3f44d106e6c","is_verified":false,"reviewed_at":null,"rejected_info":"random banana apple sad sad random apple apple dog happy","user_id":"032eb0aa-df19-4e4c-9b10-19ede9606f91","request_date":"2024-01-09T21:06:52.885Z","front_identity_card_image_link":"https://picsum.photos/200/300?random=600037378","back_identity_card_image_link":"https://picsum.photos/200/300?random=288253978","portrait_image_link":"https://picsum.photos/200/300?random=835978153","full_name":"cat random orange moon dog random orange sad cat banana","sex":true,"dob":"1975-06-05T13:50:27.728Z","identity_card_no":"123456789132","identity_card_issued_date":"2000-09-14T22:54:52.180Z","issued_by":"Công an Hà Nội"},{"id":"6bcb0c52-078d-480b-b216-9e25cfbe948b","is_verified":false,"reviewed_at":null,"rejected_info":"random random apple cat cat sad happy random sad sun","user_id":"acd91d26-4e9c-4807-94b7-57015dd554b8","request_date":"2024-01-09T21:06:52.885Z","front_identity_card_image_link":"https://picsum.photos/200/300?random=443322194","back_identity_card_image_link":"https://picsum.photos/200/300?random=319017608","portrait_image_link":"https://picsum.photos/200/300?random=309519581","full_name":"random sun moon moon apple dog moon orange moon banana","sex":false,"dob":"2004-11-11T11:02:22.933Z","identity_card_no":"123456789133","identity_card_issued_date":"2006-07-21T14:54:17.996Z","issued_by":"Công an Hà Nội"},{"id":"1c139ce5-fa6a-4c2f-8bca-e1b761946752","is_verified":false,"reviewed_at":null,"rejected_info":"apple moon orange apple cat sad apple random sun sun","user_id":"b9776123-9188-4e95-995d-44311cfe7445","request_date":"2024-01-09T21:06:52.885Z","front_identity_card_image_link":"https://picsum.photos/200/300?random=285180842","back_identity_card_image_link":"https://picsum.photos/200/300?random=771783234","portrait_image_link":"https://picsum.photos/200/300?random=758029140","full_name":"apple cat apple cat orange random cat banana orange moon","sex":true,"dob":"1998-02-17T04:23:25.053Z","identity_card_no":"123456789134","identity_card_issued_date":"2009-07-14T18:11:44.262Z","issued_by":"Công an Hà Nội"},{"id":"6aa465a3-53f0-4bfc-8189-6eb56f642a6d","is_verified":false,"reviewed_at":null,"rejected_info":"happy moon random sad moon banana apple orange happy happy","user_id":"891d88a3-3f3b-45d7-9bea-55398aa02b06","request_date":"2024-01-09T21:06:52.885Z","front_identity_card_image_link":"https://picsum.photos/200/300?random=268821146","back_identity_card_image_link":"https://picsum.photos/200/300?random=983775262","portrait_image_link":"https://picsum.photos/200/300?random=45538986","full_name":"random dog cat orange dog sad sun orange sun moon","sex":true,"dob":"1997-10-18T06:21:17.271Z","identity_card_no":"123456789135","identity_card_issued_date":"2017-03-20T16:31:53.267Z","issued_by":"Công an Hà Nội"},{"id":"dfe85536-3254-4547-80ea-f30a68c8b721","is_verified":false,"reviewed_at":null,"rejected_info":"sad sad banana banana orange happy sad sun apple random","user_id":"8bc42aed-0036-45a2-8e1d-8041afe12d23","request_date":"2024-01-09T21:06:52.885Z","front_identity_card_image_link":"https://picsum.photos/200/300?random=330046850","back_identity_card_image_link":"https://picsum.photos/200/300?random=875060351","portrait_image_link":"https://picsum.photos/200/300?random=814631986","full_name":"sun banana moon banana sad sad dog cat happy random","sex":false,"dob":"2000-01-06T09:01:18.911Z","identity_card_no":"123456789136","identity_card_issued_date":"2007-06-26T01:27:33.025Z","issued_by":"Công an Hà Nội"},{"id":"3a3845d3-f1ce-49b7-a82d-a3d7c5c02fdd","is_verified":false,"reviewed_at":null,"rejected_info":"orange random apple sad random banana dog orange moon moon","user_id":"d9f4a336-f029-4638-9815-9a0876dc159f","request_date":"2024-01-09T21:06:52.885Z","front_identity_card_image_link":"https://picsum.photos/200/300?random=469261704","back_identity_card_image_link":"https://picsum.photos/200/300?random=924087315","portrait_image_link":"https://picsum.photos/200/300?random=883985694","full_name":"sun sun banana orange happy dog sun orange orange cat","sex":true,"dob":"1985-07-04T14:03:08.427Z","identity_card_no":"123456789137","identity_card_issued_date":"2017-08-22T00:54:22.612Z","issued_by":"Công an Hà Nội"},{"id":"ede116b6-0fe2-4b68-ab5c-ea3b09d0d556","is_verified":false,"reviewed_at":null,"rejected_info":"sad banana sun moon sun cat dog moon random banana","user_id":"8f021f08-c21e-4d5b-8880-bd8954f37e45","request_date":"2024-01-09T21:06:52.885Z","front_identity_card_image_link":"https://picsum.photos/200/300?random=831914431","back_identity_card_image_link":"https://picsum.photos/200/300?random=740790761","portrait_image_link":"https://picsum.photos/200/300?random=62801060","full_name":"random dog sad apple happy cat happy orange cat happy","sex":false,"dob":"1978-02-28T07:05:05.649Z","identity_card_no":"123456789138","identity_card_issued_date":"2022-12-26T17:56:53.930Z","issued_by":"Công an Hà Nội"},{"id":"d5633d9f-b4e2-4ce7-86b7-f8bdd8c530e0","is_verified":false,"reviewed_at":null,"rejected_info":"happy banana moon random banana banana orange random moon apple","user_id":"d9f4a336-f029-4638-9815-9a0876dc159f","request_date":"2024-01-09T21:06:52.885Z","front_identity_card_image_link":"https://picsum.photos/200/300?random=488986114","back_identity_card_image_link":"https://picsum.photos/200/300?random=45136868","portrait_image_link":"https://picsum.photos/200/300?random=902652570","full_name":"sun banana banana dog banana happy sun orange moon cat","sex":true,"dob":"1982-05-12T02:52:27.377Z","identity_card_no":"123456789139","identity_card_issued_date":"2004-01-24T19:53:26.039Z","issued_by":"Công an Hà Nội"},{"id":"4637a017-ab59-438e-9c63-2f8f8278e4bb","is_verified":false,"reviewed_at":null,"rejected_info":"dog moon sad banana moon banana moon happy moon banana","user_id":"8bc42aed-0036-45a2-8e1d-8041afe12d23","request_date":"2024-01-09T21:06:52.885Z","front_identity_card_image_link":"https://picsum.photos/200/300?random=121417129","back_identity_card_image_link":"https://picsum.photos/200/300?random=992977260","portrait_image_link":"https://picsum.photos/200/300?random=61380021","full_name":"happy sad cat random moon dog dog banana banana random","sex":false,"dob":"2016-02-19T05:47:56.180Z","identity_card_no":"123456789140","identity_card_issued_date":"2011-09-25T03:41:59.796Z","issued_by":"Công an Hà Nội"},{"id":"6f03ae6c-29b1-473e-a63e-53307fd77679","is_verified":false,"reviewed_at":null,"rejected_info":"moon banana random sad random happy moon happy moon moon","user_id":"5ebc825b-48dc-4b33-910d-a711999934c4","request_date":"2024-01-09T21:06:52.885Z","front_identity_card_image_link":"https://picsum.photos/200/300?random=763191439","back_identity_card_image_link":"https://picsum.photos/200/300?random=886931599","portrait_image_link":"https://picsum.photos/200/300?random=698179671","full_name":"random cat apple moon moon cat random random orange banana","sex":true,"dob":"2016-08-24T08:41:16.367Z","identity_card_no":"123456789141","identity_card_issued_date":"2014-09-20T11:14:26.991Z","issued_by":"Công an Hà Nội"},{"id":"4c0b6046-f88e-45c0-b3cf-77cb570ad328","is_verified":true,"reviewed_at":"2024-01-09T21:06:52.885Z","rejected_info":null,"user_id":"b9776123-9188-4e95-995d-44311cfe7445","request_date":"2024-01-09T21:06:52.885Z","front_identity_card_image_link":"https://picsum.photos/200/300?random=280479131","back_identity_card_image_link":"https://picsum.photos/200/300?random=745333569","portrait_image_link":"https://picsum.photos/200/300?random=702855","full_name":"sad sun banana orange apple sun sad sun sun sun","sex":true,"dob":"1987-12-21T06:45:00.015Z","identity_card_no":"123456789142","identity_card_issued_date":"2016-06-12T04:37:45.017Z","issued_by":"Công an Hà Nội"},{"id":"b97a3e52-80ee-41fb-ae0a-11b0a98a8201","is_verified":false,"reviewed_at":null,"rejected_info":"dog dog orange cat sun happy moon random orange apple","user_id":"5ebc825b-48dc-4b33-910d-a711999934c4","request_date":"2024-01-09T21:06:52.885Z","front_identity_card_image_link":"https://picsum.photos/200/300?random=51676543","back_identity_card_image_link":"https://picsum.photos/200/300?random=680440028","portrait_image_link":"https://picsum.photos/200/300?random=175605364","full_name":"banana sun random happy orange banana moon sad orange random","sex":true,"dob":"2022-04-29T23:13:14.351Z","identity_card_no":"123456789143","identity_card_issued_date":"2008-02-23T02:20:48.641Z","issued_by":"Công an Hà Nội"},{"id":"537e8392-fdfe-42b1-ae15-56f39f9d8b0c","is_verified":false,"reviewed_at":null,"rejected_info":"orange banana sad sun cat sad moon sad happy moon","user_id":"032eb0aa-df19-4e4c-9b10-19ede9606f91","request_date":"2024-01-09T21:06:52.885Z","front_identity_card_image_link":"https://picsum.photos/200/300?random=580918015","back_identity_card_image_link":"https://picsum.photos/200/300?random=949644661","portrait_image_link":"https://picsum.photos/200/300?random=999960851","full_name":"cat moon apple sad sad sad sun happy random cat","sex":false,"dob":"1991-01-02T21:07:46.205Z","identity_card_no":"123456789144","identity_card_issued_date":"2002-06-02T12:23:08.895Z","issued_by":"Công an Hà Nội"},{"id":"25337928-1cdb-4c10-9f2a-bf571653cf17","is_verified":false,"reviewed_at":null,"rejected_info":"banana apple apple cat apple sun apple sun random banana","user_id":"d45afc3e-05e0-41a7-b38d-7e801bf92f04","request_date":"2024-01-09T21:06:52.885Z","front_identity_card_image_link":"https://picsum.photos/200/300?random=142007935","back_identity_card_image_link":"https://picsum.photos/200/300?random=859675983","portrait_image_link":"https://picsum.photos/200/300?random=513121066","full_name":"orange banana moon sad random random cat orange sad cat","sex":true,"dob":"1975-12-29T14:11:54.838Z","identity_card_no":"123456789145","identity_card_issued_date":"2003-08-08T01:13:39.693Z","issued_by":"Công an Hà Nội"},{"id":"e28d709f-8812-46cd-8aac-d472a3c91d0f","is_verified":true,"reviewed_at":"2024-01-09T21:06:52.885Z","rejected_info":null,"user_id":"1a9a5785-721a-4bb5-beb7-9d752e2070d4","request_date":"2024-01-09T21:06:52.885Z","front_identity_card_image_link":"https://picsum.photos/200/300?random=663850715","back_identity_card_image_link":"https://picsum.photos/200/300?random=712561742","portrait_image_link":"https://picsum.photos/200/300?random=647479621","full_name":"sad random sun dog happy apple dog banana happy random","sex":false,"dob":"1998-11-05T18:06:17.553Z","identity_card_no":"123456789146","identity_card_issued_date":"2010-07-24T05:32:21.762Z","issued_by":"Công an Hà Nội"},{"id":"28b137f0-e1bb-4f4f-8ae4-bc6a3dad4142","is_verified":false,"reviewed_at":null,"rejected_info":"random banana banana sun happy cat banana sun cat banana","user_id":"8f021f08-c21e-4d5b-8880-bd8954f37e45","request_date":"2024-01-09T21:06:52.885Z","front_identity_card_image_link":"https://picsum.photos/200/300?random=160392808","back_identity_card_image_link":"https://picsum.photos/200/300?random=943498124","portrait_image_link":"https://picsum.photos/200/300?random=965959214","full_name":"orange sun random apple apple banana apple orange dog cat","sex":true,"dob":"2002-03-08T10:22:47.021Z","identity_card_no":"123456789147","identity_card_issued_date":"2012-02-26T16:59:18.815Z","issued_by":"Công an Hà Nội"},{"id":"3decd2f1-4ea2-4cb1-acb5-9d435809f21a","is_verified":false,"reviewed_at":null,"rejected_info":"happy apple banana happy orange moon random sad sun dog","user_id":"a9eb0d7d-025b-48fa-9ff7-b792b249c159","request_date":"2024-01-09T21:06:52.885Z","front_identity_card_image_link":"https://picsum.photos/200/300?random=916607396","back_identity_card_image_link":"https://picsum.photos/200/300?random=786123573","portrait_image_link":"https://picsum.photos/200/300?random=146117452","full_name":"dog dog happy sad orange apple cat dog random sad","sex":true,"dob":"1980-11-15T08:30:26.361Z","identity_card_no":"123456789148","identity_card_issued_date":"2012-09-13T17:23:41.766Z","issued_by":"Công an Hà Nội"},{"id":"47258823-b982-4436-a9d6-365b9d1aca7d","is_verified":false,"reviewed_at":null,"rejected_info":"cat happy sun sad moon sad banana sun random banana","user_id":"436660d3-98b4-45d9-98c8-098c603a442b","request_date":"2024-01-09T21:06:52.885Z","front_identity_card_image_link":"https://picsum.photos/200/300?random=893758683","back_identity_card_image_link":"https://picsum.photos/200/300?random=144374245","portrait_image_link":"https://picsum.photos/200/300?random=453705395","full_name":"random sun sun happy banana happy banana apple orange dog","sex":false,"dob":"1997-07-25T04:54:38.373Z","identity_card_no":"123456789149","identity_card_issued_date":"2019-03-03T22:24:54.280Z","issued_by":"Công an Hà Nội"},{"id":"eb80cc73-6447-495f-bd9d-c1f2f7d9bc3e","is_verified":false,"reviewed_at":null,"rejected_info":"apple moon happy orange moon banana cat sun happy cat","user_id":"b9776123-9188-4e95-995d-44311cfe7445","request_date":"2024-01-09T21:06:52.885Z","front_identity_card_image_link":"https://picsum.photos/200/300?random=68503236","back_identity_card_image_link":"https://picsum.photos/200/300?random=340529815","portrait_image_link":"https://picsum.photos/200/300?random=259012225","full_name":"dog cat happy orange sun apple sun apple orange cat","sex":true,"dob":"2000-07-29T20:19:31.700Z","identity_card_no":"123456789150","identity_card_issued_date":"2023-02-05T11:58:13.510Z","issued_by":"Công an Hà Nội"},{"id":"eb27e3c8-7756-4b61-aa61-abc08788eca8","is_verified":false,"reviewed_at":null,"rejected_info":"cat sad moon random cat banana orange orange apple banana","user_id":"5ebc825b-48dc-4b33-910d-a711999934c4","request_date":"2024-01-09T21:06:52.885Z","front_identity_card_image_link":"https://picsum.photos/200/300?random=776956429","back_identity_card_image_link":"https://picsum.photos/200/300?random=864801455","portrait_image_link":"https://picsum.photos/200/300?random=614465180","full_name":"dog dog apple banana sad moon sun moon happy moon","sex":false,"dob":"1982-09-09T12:09:21.836Z","identity_card_no":"123456789151","identity_card_issued_date":"2020-02-04T04:35:36.576Z","issued_by":"Công an Hà Nội"},{"id":"fdd0c672-6341-43a4-94f7-533c60f6e369","is_verified":false,"reviewed_at":null,"rejected_info":"orange moon sun sun orange banana apple apple cat sad","user_id":"acd91d26-4e9c-4807-94b7-57015dd554b8","request_date":"2024-01-09T21:06:52.885Z","front_identity_card_image_link":"https://picsum.photos/200/300?random=244422981","back_identity_card_image_link":"https://picsum.photos/200/300?random=757721797","portrait_image_link":"https://picsum.photos/200/300?random=402694416","full_name":"cat dog banana sun random random sun dog sad orange","sex":false,"dob":"2007-08-03T21:02:51.316Z","identity_card_no":"123456789152","identity_card_issued_date":"2005-06-24T18:02:04.242Z","issued_by":"Công an Hà Nội"},{"id":"38c20d3c-59f3-4626-97c9-51aa49b735ef","is_verified":false,"reviewed_at":null,"rejected_info":"sun random random cat sun happy moon happy orange sad","user_id":"8f021f08-c21e-4d5b-8880-bd8954f37e45","request_date":"2024-01-09T21:06:52.885Z","front_identity_card_image_link":"https://picsum.photos/200/300?random=237866261","back_identity_card_image_link":"https://picsum.photos/200/300?random=955536255","portrait_image_link":"https://picsum.photos/200/300?random=148015491","full_name":"apple sad sad happy apple dog cat cat sun dog","sex":false,"dob":"2005-04-04T22:42:05.208Z","identity_card_no":"123456789153","identity_card_issued_date":"2004-09-02T19:35:49.202Z","issued_by":"Công an Hà Nội"},{"id":"e5e106d2-0604-4734-9aa6-1458b726cb70","is_verified":false,"reviewed_at":null,"rejected_info":"banana moon moon banana sad happy dog banana orange random","user_id":"1a9a5785-721a-4bb5-beb7-9d752e2070d4","request_date":"2024-01-09T21:06:52.885Z","front_identity_card_image_link":"https://picsum.photos/200/300?random=837502133","back_identity_card_image_link":"https://picsum.photos/200/300?random=214966906","portrait_image_link":"https://picsum.photos/200/300?random=939458021","full_name":"banana orange happy sad cat sun dog dog random happy","sex":false,"dob":"1982-08-05T03:38:01.251Z","identity_card_no":"123456789154","identity_card_issued_date":"2015-04-21T01:10:58.111Z","issued_by":"Công an Hà Nội"},{"id":"96039d61-64f6-4056-b043-15d7131f6219","is_verified":false,"reviewed_at":null,"rejected_info":"orange sad dog dog happy banana cat moon happy sun","user_id":"eb9c2609-0dc7-426b-9347-d59795d517a9","request_date":"2024-01-09T21:06:52.885Z","front_identity_card_image_link":"https://picsum.photos/200/300?random=789912097","back_identity_card_image_link":"https://picsum.photos/200/300?random=873155543","portrait_image_link":"https://picsum.photos/200/300?random=520746418","full_name":"happy random orange sun sad cat random cat moon happy","sex":false,"dob":"1989-08-01T22:56:32.983Z","identity_card_no":"123456789155","identity_card_issued_date":"2010-11-24T02:12:16.880Z","issued_by":"Công an Hà Nội"},{"id":"8e980cd7-dbaa-4b25-94b9-e3a5cae76bf8","is_verified":false,"reviewed_at":null,"rejected_info":"moon banana moon cat apple cat dog happy cat cat","user_id":"a9eb0d7d-025b-48fa-9ff7-b792b249c159","request_date":"2024-01-09T21:06:52.885Z","front_identity_card_image_link":"https://picsum.photos/200/300?random=905023566","back_identity_card_image_link":"https://picsum.photos/200/300?random=807722373","portrait_image_link":"https://picsum.photos/200/300?random=552846509","full_name":"banana banana random sad random cat happy sun cat random","sex":true,"dob":"1984-07-02T04:21:29.113Z","identity_card_no":"123456789156","identity_card_issued_date":"2010-11-20T10:11:05.657Z","issued_by":"Công an Hà Nội"},{"id":"39c5b6b2-efe7-41f8-9f18-f76bd2e27a49","is_verified":false,"reviewed_at":null,"rejected_info":"banana cat dog dog apple happy apple sun sad moon","user_id":"b9776123-9188-4e95-995d-44311cfe7445","request_date":"2024-01-09T21:06:52.885Z","front_identity_card_image_link":"https://picsum.photos/200/300?random=237652094","back_identity_card_image_link":"https://picsum.photos/200/300?random=94476409","portrait_image_link":"https://picsum.photos/200/300?random=763607133","full_name":"random apple sun happy sad apple dog random happy happy","sex":true,"dob":"1979-01-23T02:12:13.249Z","identity_card_no":"123456789157","identity_card_issued_date":"2013-12-20T14:12:44.884Z","issued_by":"Công an Hà Nội"},{"id":"65dfe67e-1fbe-47c5-973e-6b023454ddf4","is_verified":false,"reviewed_at":null,"rejected_info":"sad sad random cat sun dog sun cat moon random","user_id":"1a9a5785-721a-4bb5-beb7-9d752e2070d4","request_date":"2024-01-09T21:06:52.885Z","front_identity_card_image_link":"https://picsum.photos/200/300?random=280677814","back_identity_card_image_link":"https://picsum.photos/200/300?random=449209782","portrait_image_link":"https://picsum.photos/200/300?random=237069730","full_name":"orange happy random banana sun apple apple apple banana happy","sex":false,"dob":"2020-05-06T23:47:08.721Z","identity_card_no":"123456789158","identity_card_issued_date":"2004-09-27T11:21:36.956Z","issued_by":"Công an Hà Nội"},{"id":"ea0749fd-cfcb-49d3-86f8-8ff3ce144afd","is_verified":false,"reviewed_at":null,"rejected_info":"sun moon banana moon cat dog random random happy sun","user_id":"8bc42aed-0036-45a2-8e1d-8041afe12d23","request_date":"2024-01-09T21:06:52.885Z","front_identity_card_image_link":"https://picsum.photos/200/300?random=838888468","back_identity_card_image_link":"https://picsum.photos/200/300?random=959736789","portrait_image_link":"https://picsum.photos/200/300?random=186944491","full_name":"sun apple cat dog happy random banana happy sad moon","sex":true,"dob":"1979-06-10T13:53:43.872Z","identity_card_no":"123456789159","identity_card_issued_date":"2005-07-25T13:42:57.581Z","issued_by":"Công an Hà Nội"},{"id":"0157cab8-1d68-4feb-bd92-fbf0c1753271","is_verified":false,"reviewed_at":null,"rejected_info":"random random cat random sad cat sad cat orange banana","user_id":"5ebc825b-48dc-4b33-910d-a711999934c4","request_date":"2024-01-09T21:06:52.885Z","front_identity_card_image_link":"https://picsum.photos/200/300?random=653864002","back_identity_card_image_link":"https://picsum.photos/200/300?random=11586611","portrait_image_link":"https://picsum.photos/200/300?random=532778046","full_name":"banana moon happy orange random random orange random sad happy","sex":true,"dob":"2002-12-06T05:53:47.230Z","identity_card_no":"123456789160","identity_card_issued_date":"2018-05-29T22:31:10.098Z","issued_by":"Công an Hà Nội"},{"id":"9ec06e3b-95de-43d9-bff2-56fd24f6b30a","is_verified":false,"reviewed_at":null,"rejected_info":"banana happy banana moon apple moon cat orange banana random","user_id":"346ce7ff-9c1e-43f5-8450-1296ece15692","request_date":"2024-01-09T21:06:52.885Z","front_identity_card_image_link":"https://picsum.photos/200/300?random=689200933","back_identity_card_image_link":"https://picsum.photos/200/300?random=417131688","portrait_image_link":"https://picsum.photos/200/300?random=808244119","full_name":"apple happy moon sun sun cat orange cat apple dog","sex":false,"dob":"1981-07-02T22:21:26.273Z","identity_card_no":"123456789161","identity_card_issued_date":"2023-07-03T17:12:04.423Z","issued_by":"Công an Hà Nội"},{"id":"34458f5b-ec42-41ac-a997-337e07fd9935","is_verified":false,"reviewed_at":null,"rejected_info":"cat apple happy happy dog moon moon apple dog sad","user_id":"acd91d26-4e9c-4807-94b7-57015dd554b8","request_date":"2024-01-09T21:06:52.885Z","front_identity_card_image_link":"https://picsum.photos/200/300?random=137737708","back_identity_card_image_link":"https://picsum.photos/200/300?random=808613680","portrait_image_link":"https://picsum.photos/200/300?random=62111245","full_name":"banana dog random apple orange dog happy moon random banana","sex":true,"dob":"2002-10-23T06:42:11.678Z","identity_card_no":"123456789162","identity_card_issued_date":"2016-03-05T18:03:27.204Z","issued_by":"Công an Hà Nội"},{"id":"53a4ee18-1eea-4561-8a9d-51e30570ca28","is_verified":false,"reviewed_at":null,"rejected_info":"sun sun banana apple banana moon cat dog dog random","user_id":"28223664-4747-424e-b2e3-27ace26bc553","request_date":"2024-01-09T21:06:52.885Z","front_identity_card_image_link":"https://picsum.photos/200/300?random=345142218","back_identity_card_image_link":"https://picsum.photos/200/300?random=810755424","portrait_image_link":"https://picsum.photos/200/300?random=584417821","full_name":"random sad banana cat happy dog banana random happy happy","sex":false,"dob":"1997-12-04T08:50:17.666Z","identity_card_no":"123456789163","identity_card_issued_date":"2003-06-17T08:59:54.649Z","issued_by":"Công an Hà Nội"},{"id":"ad8034c8-cb05-4b0c-b631-53a4f76cc3f7","is_verified":false,"reviewed_at":null,"rejected_info":"random happy banana sun sun banana sad dog sun sad","user_id":"8f021f08-c21e-4d5b-8880-bd8954f37e45","request_date":"2024-01-09T21:06:52.885Z","front_identity_card_image_link":"https://picsum.photos/200/300?random=262463337","back_identity_card_image_link":"https://picsum.photos/200/300?random=264093740","portrait_image_link":"https://picsum.photos/200/300?random=774607155","full_name":"dog sad orange dog happy banana random moon cat orange","sex":true,"dob":"1990-09-27T13:20:43.726Z","identity_card_no":"123456789164","identity_card_issued_date":"2010-08-26T02:25:54.809Z","issued_by":"Công an Hà Nội"},{"id":"b15fbc52-9a73-4489-933d-bd8d20a43c51","is_verified":false,"reviewed_at":null,"rejected_info":"banana happy moon apple apple dog happy sad orange random","user_id":"346ce7ff-9c1e-43f5-8450-1296ece15692","request_date":"2024-01-09T21:06:52.885Z","front_identity_card_image_link":"https://picsum.photos/200/300?random=671954521","back_identity_card_image_link":"https://picsum.photos/200/300?random=625724788","portrait_image_link":"https://picsum.photos/200/300?random=30256754","full_name":"sun sad cat apple apple banana moon happy happy banana","sex":true,"dob":"1978-01-08T21:32:52.382Z","identity_card_no":"123456789165","identity_card_issued_date":"2007-03-10T18:50:44.417Z","issued_by":"Công an Hà Nội"},{"id":"d26284a0-0e24-4806-864c-31ea4ad67bc2","is_verified":true,"reviewed_at":"2024-01-09T21:06:52.885Z","rejected_info":null,"user_id":"346ce7ff-9c1e-43f5-8450-1296ece15692","request_date":"2024-01-09T21:06:52.885Z","front_identity_card_image_link":"https://picsum.photos/200/300?random=566760402","back_identity_card_image_link":"https://picsum.photos/200/300?random=355583486","portrait_image_link":"https://picsum.photos/200/300?random=77514273","full_name":"banana sad moon orange random sad apple happy cat sad","sex":true,"dob":"1978-09-17T16:34:50.202Z","identity_card_no":"123456789166","identity_card_issued_date":"2011-11-02T23:57:55.525Z","issued_by":"Công an Hà Nội"},{"id":"f29d5c0a-12a5-4c02-b21a-a7b053157472","is_verified":true,"reviewed_at":"2024-01-09T21:06:52.885Z","rejected_info":null,"user_id":"b9776123-9188-4e95-995d-44311cfe7445","request_date":"2024-01-09T21:06:52.885Z","front_identity_card_image_link":"https://picsum.photos/200/300?random=440626432","back_identity_card_image_link":"https://picsum.photos/200/300?random=832982215","portrait_image_link":"https://picsum.photos/200/300?random=778255509","full_name":"dog orange banana happy cat cat apple dog moon banana","sex":true,"dob":"1982-07-25T03:57:24.965Z","identity_card_no":"123456789167","identity_card_issued_date":"2018-08-26T07:05:56.735Z","issued_by":"Công an Hà Nội"},{"id":"09f8916d-b680-4110-9502-5156ad6adc57","is_verified":false,"reviewed_at":null,"rejected_info":"dog sun sad sad cat sad moon apple banana dog","user_id":"436660d3-98b4-45d9-98c8-098c603a442b","request_date":"2024-01-09T21:06:52.885Z","front_identity_card_image_link":"https://picsum.photos/200/300?random=766101183","back_identity_card_image_link":"https://picsum.photos/200/300?random=627377752","portrait_image_link":"https://picsum.photos/200/300?random=478013649","full_name":"moon sun dog moon apple banana orange sad happy apple","sex":false,"dob":"1985-10-03T02:32:37.268Z","identity_card_no":"123456789168","identity_card_issued_date":"2021-04-09T12:41:36.163Z","issued_by":"Công an Hà Nội"},{"id":"a41f72d4-5bc9-4344-bb59-ca05adaac977","is_verified":false,"reviewed_at":null,"rejected_info":"random cat happy sun sun sad cat cat orange random","user_id":"5ebc825b-48dc-4b33-910d-a711999934c4","request_date":"2024-01-09T21:06:52.885Z","front_identity_card_image_link":"https://picsum.photos/200/300?random=846367730","back_identity_card_image_link":"https://picsum.photos/200/300?random=609724371","portrait_image_link":"https://picsum.photos/200/300?random=1312646","full_name":"random banana sad orange orange banana dog sun orange sun","sex":false,"dob":"1981-03-09T05:42:00.144Z","identity_card_no":"123456789169","identity_card_issued_date":"2009-01-22T08:10:04.625Z","issued_by":"Công an Hà Nội"},{"id":"25406a13-32fd-40ba-bb6b-b20be9e70207","is_verified":false,"reviewed_at":null,"rejected_info":"dog banana random sun dog moon happy orange random sad","user_id":"a9eb0d7d-025b-48fa-9ff7-b792b249c159","request_date":"2024-01-09T21:06:52.885Z","front_identity_card_image_link":"https://picsum.photos/200/300?random=291174408","back_identity_card_image_link":"https://picsum.photos/200/300?random=37728655","portrait_image_link":"https://picsum.photos/200/300?random=192675882","full_name":"orange happy random sad moon sad moon sun apple happy","sex":true,"dob":"2010-02-20T03:49:46.471Z","identity_card_no":"123456789170","identity_card_issued_date":"2020-11-19T12:26:26.483Z","issued_by":"Công an Hà Nội"},{"id":"767d3074-592e-4681-a4c2-24318e901523","is_verified":false,"reviewed_at":null,"rejected_info":"happy cat moon banana apple dog banana happy banana apple","user_id":"a9eb0d7d-025b-48fa-9ff7-b792b249c159","request_date":"2024-01-09T21:06:52.885Z","front_identity_card_image_link":"https://picsum.photos/200/300?random=931974861","back_identity_card_image_link":"https://picsum.photos/200/300?random=1849404","portrait_image_link":"https://picsum.photos/200/300?random=41429745","full_name":"dog apple sun moon random cat apple banana cat sun","sex":false,"dob":"2007-11-18T22:09:00.726Z","identity_card_no":"123456789171","identity_card_issued_date":"2005-11-13T19:47:17.552Z","issued_by":"Công an Hà Nội"},{"id":"0754552d-e0eb-4a3c-a728-c5d0f0193231","is_verified":false,"reviewed_at":null,"rejected_info":"cat random random happy sad moon cat moon sun cat","user_id":"280d8b28-07ae-43e7-a54e-6468b6acf519","request_date":"2024-01-09T21:06:52.885Z","front_identity_card_image_link":"https://picsum.photos/200/300?random=641593727","back_identity_card_image_link":"https://picsum.photos/200/300?random=115310289","portrait_image_link":"https://picsum.photos/200/300?random=258847354","full_name":"sun moon cat cat orange dog moon apple dog moon","sex":true,"dob":"1979-09-24T03:25:36.042Z","identity_card_no":"123456789172","identity_card_issued_date":"2014-01-03T22:43:06.617Z","issued_by":"Công an Hà Nội"},{"id":"2e0a3eb8-8fe9-4f86-a11b-18da14cd5708","is_verified":false,"reviewed_at":null,"rejected_info":"sad sad apple banana dog banana happy random random cat","user_id":"d45afc3e-05e0-41a7-b38d-7e801bf92f04","request_date":"2024-01-09T21:06:52.885Z","front_identity_card_image_link":"https://picsum.photos/200/300?random=62720721","back_identity_card_image_link":"https://picsum.photos/200/300?random=283727189","portrait_image_link":"https://picsum.photos/200/300?random=2920192","full_name":"sad dog random banana orange orange sun dog cat sad","sex":false,"dob":"1978-10-12T22:22:07.481Z","identity_card_no":"123456789173","identity_card_issued_date":"2000-06-22T00:44:25.067Z","issued_by":"Công an Hà Nội"},{"id":"8b979acb-171b-4288-835e-db8be5838d86","is_verified":false,"reviewed_at":null,"rejected_info":"sun dog banana moon sun cat orange sad orange apple","user_id":"436660d3-98b4-45d9-98c8-098c603a442b","request_date":"2024-01-09T21:06:52.885Z","front_identity_card_image_link":"https://picsum.photos/200/300?random=500065769","back_identity_card_image_link":"https://picsum.photos/200/300?random=142302832","portrait_image_link":"https://picsum.photos/200/300?random=484015569","full_name":"moon happy sun orange apple happy sun sad random sun","sex":false,"dob":"1974-05-28T06:31:02.564Z","identity_card_no":"123456789174","identity_card_issued_date":"2015-08-27T02:33:13.271Z","issued_by":"Công an Hà Nội"},{"id":"09cb0cce-c940-4f68-97f7-9fc6502a3663","is_verified":false,"reviewed_at":null,"rejected_info":"sad happy sun sun cat moon apple orange moon dog","user_id":"acd91d26-4e9c-4807-94b7-57015dd554b8","request_date":"2024-01-09T21:06:52.885Z","front_identity_card_image_link":"https://picsum.photos/200/300?random=382930231","back_identity_card_image_link":"https://picsum.photos/200/300?random=244547965","portrait_image_link":"https://picsum.photos/200/300?random=166682060","full_name":"banana dog sad banana sun apple cat happy dog orange","sex":false,"dob":"1981-11-28T05:33:39.954Z","identity_card_no":"123456789175","identity_card_issued_date":"2003-10-10T18:26:38.825Z","issued_by":"Công an Hà Nội"},{"id":"943b9106-fae1-4f1f-b266-33911a0a1087","is_verified":false,"reviewed_at":null,"rejected_info":"dog banana random dog apple orange random sad sad happy","user_id":"28223664-4747-424e-b2e3-27ace26bc553","request_date":"2024-01-09T21:06:52.885Z","front_identity_card_image_link":"https://picsum.photos/200/300?random=146813197","back_identity_card_image_link":"https://picsum.photos/200/300?random=772696535","portrait_image_link":"https://picsum.photos/200/300?random=772912520","full_name":"dog banana apple cat moon moon moon sun happy sun","sex":true,"dob":"2015-07-15T00:08:51.972Z","identity_card_no":"123456789176","identity_card_issued_date":"2021-07-09T13:51:34.571Z","issued_by":"Công an Hà Nội"},{"id":"e3755f55-5a82-4107-b26c-bc402e0da6e5","is_verified":false,"reviewed_at":null,"rejected_info":"sun cat moon apple moon sun random moon cat moon","user_id":"8bc42aed-0036-45a2-8e1d-8041afe12d23","request_date":"2024-01-09T21:06:52.885Z","front_identity_card_image_link":"https://picsum.photos/200/300?random=149794578","back_identity_card_image_link":"https://picsum.photos/200/300?random=43880167","portrait_image_link":"https://picsum.photos/200/300?random=131002313","full_name":"apple sun orange apple dog moon cat banana dog orange","sex":true,"dob":"2012-09-13T18:48:33.611Z","identity_card_no":"123456789177","identity_card_issued_date":"2008-07-23T02:52:36.230Z","issued_by":"Công an Hà Nội"},{"id":"d000cf4c-b9df-416f-a58e-162aef696590","is_verified":false,"reviewed_at":null,"rejected_info":"banana dog apple random dog happy sad happy random orange","user_id":"a9eb0d7d-025b-48fa-9ff7-b792b249c159","request_date":"2024-01-09T21:06:52.885Z","front_identity_card_image_link":"https://picsum.photos/200/300?random=879017732","back_identity_card_image_link":"https://picsum.photos/200/300?random=804313433","portrait_image_link":"https://picsum.photos/200/300?random=305044459","full_name":"moon sad orange apple dog happy sad sun orange orange","sex":true,"dob":"1984-01-17T16:55:17.630Z","identity_card_no":"123456789178","identity_card_issued_date":"2009-05-31T07:09:55.158Z","issued_by":"Công an Hà Nội"},{"id":"77ae01f8-921a-4e34-9cca-7aaccab52210","is_verified":false,"reviewed_at":null,"rejected_info":"random moon orange sun orange orange dog orange cat apple","user_id":"891d88a3-3f3b-45d7-9bea-55398aa02b06","request_date":"2024-01-09T21:06:52.885Z","front_identity_card_image_link":"https://picsum.photos/200/300?random=395464077","back_identity_card_image_link":"https://picsum.photos/200/300?random=81272776","portrait_image_link":"https://picsum.photos/200/300?random=242275991","full_name":"sad cat dog sad cat dog orange random sun cat","sex":true,"dob":"2009-01-11T15:02:07.650Z","identity_card_no":"123456789179","identity_card_issued_date":"2009-10-15T16:49:44.591Z","issued_by":"Công an Hà Nội"},{"id":"4a76b790-1f8e-4086-8ab3-a2f9f314f3a2","is_verified":false,"reviewed_at":null,"rejected_info":"random sad random dog apple cat apple sad cat apple","user_id":"acd91d26-4e9c-4807-94b7-57015dd554b8","request_date":"2024-01-09T21:06:52.885Z","front_identity_card_image_link":"https://picsum.photos/200/300?random=399391778","back_identity_card_image_link":"https://picsum.photos/200/300?random=152743495","portrait_image_link":"https://picsum.photos/200/300?random=555241920","full_name":"moon sun sad cat moon banana apple apple banana sun","sex":false,"dob":"1973-02-11T19:47:58.314Z","identity_card_no":"123456789180","identity_card_issued_date":"2016-05-26T15:48:48.287Z","issued_by":"Công an Hà Nội"},{"id":"9085073b-d0f7-4417-8a29-e026390114e2","is_verified":false,"reviewed_at":null,"rejected_info":"sun cat moon random apple cat happy sad moon dog","user_id":"eb9c2609-0dc7-426b-9347-d59795d517a9","request_date":"2024-01-09T21:06:52.885Z","front_identity_card_image_link":"https://picsum.photos/200/300?random=262120452","back_identity_card_image_link":"https://picsum.photos/200/300?random=6044522","portrait_image_link":"https://picsum.photos/200/300?random=55999911","full_name":"happy sad cat moon sun dog orange sad moon orange","sex":false,"dob":"2018-11-23T23:26:21.706Z","identity_card_no":"123456789181","identity_card_issued_date":"2012-06-27T22:25:47.133Z","issued_by":"Công an Hà Nội"},{"id":"cb859044-4d92-4e87-947a-62e82b7e01de","is_verified":false,"reviewed_at":null,"rejected_info":"sun banana banana sad random moon sun orange orange sad","user_id":"032eb0aa-df19-4e4c-9b10-19ede9606f91","request_date":"2024-01-09T21:06:52.885Z","front_identity_card_image_link":"https://picsum.photos/200/300?random=530741136","back_identity_card_image_link":"https://picsum.photos/200/300?random=536159148","portrait_image_link":"https://picsum.photos/200/300?random=894839396","full_name":"banana dog cat banana cat banana happy dog sad apple","sex":false,"dob":"2000-09-05T18:23:10.845Z","identity_card_no":"123456789182","identity_card_issued_date":"2021-03-23T23:54:47.501Z","issued_by":"Công an Hà Nội"},{"id":"a448702e-1d6c-4569-b564-20f5fcc02894","is_verified":false,"reviewed_at":null,"rejected_info":"happy dog cat banana moon sad random banana random banana","user_id":"eb9c2609-0dc7-426b-9347-d59795d517a9","request_date":"2024-01-09T21:06:52.885Z","front_identity_card_image_link":"https://picsum.photos/200/300?random=495183077","back_identity_card_image_link":"https://picsum.photos/200/300?random=146158871","portrait_image_link":"https://picsum.photos/200/300?random=711324683","full_name":"dog sun moon dog random banana cat happy orange sun","sex":false,"dob":"2000-03-21T17:37:20.306Z","identity_card_no":"123456789183","identity_card_issued_date":"2014-04-30T23:02:16.972Z","issued_by":"Công an Hà Nội"},{"id":"3db6ba2a-cbc2-4074-971b-f02a249be6da","is_verified":false,"reviewed_at":null,"rejected_info":"dog random cat random sun cat dog orange happy sun","user_id":"d45afc3e-05e0-41a7-b38d-7e801bf92f04","request_date":"2024-01-09T21:06:52.885Z","front_identity_card_image_link":"https://picsum.photos/200/300?random=51569137","back_identity_card_image_link":"https://picsum.photos/200/300?random=701785591","portrait_image_link":"https://picsum.photos/200/300?random=937472143","full_name":"happy moon banana moon sad dog cat orange random apple","sex":false,"dob":"1982-07-17T20:45:19.927Z","identity_card_no":"123456789184","identity_card_issued_date":"2016-01-16T21:03:02.373Z","issued_by":"Công an Hà Nội"},{"id":"73b64724-246c-44f2-a40b-ad1ed6b93212","is_verified":false,"reviewed_at":null,"rejected_info":"cat dog moon dog apple cat random sun banana apple","user_id":"032eb0aa-df19-4e4c-9b10-19ede9606f91","request_date":"2024-01-09T21:06:52.885Z","front_identity_card_image_link":"https://picsum.photos/200/300?random=553312243","back_identity_card_image_link":"https://picsum.photos/200/300?random=964942863","portrait_image_link":"https://picsum.photos/200/300?random=911183068","full_name":"orange sad dog apple sun orange moon dog banana apple","sex":false,"dob":"1992-04-26T16:23:27.922Z","identity_card_no":"123456789185","identity_card_issued_date":"2004-05-08T18:34:30.954Z","issued_by":"Công an Hà Nội"},{"id":"51faf9a1-0515-42c1-9428-1d910e2592a0","is_verified":false,"reviewed_at":null,"rejected_info":"apple sad apple banana apple apple happy random sun moon","user_id":"280d8b28-07ae-43e7-a54e-6468b6acf519","request_date":"2024-01-09T21:06:52.885Z","front_identity_card_image_link":"https://picsum.photos/200/300?random=419262209","back_identity_card_image_link":"https://picsum.photos/200/300?random=180632459","portrait_image_link":"https://picsum.photos/200/300?random=34145034","full_name":"dog orange sun happy dog sad apple random dog banana","sex":true,"dob":"2022-05-06T11:46:22.646Z","identity_card_no":"123456789186","identity_card_issued_date":"2022-06-21T04:01:46.492Z","issued_by":"Công an Hà Nội"},{"id":"cf6044c4-6c1c-4de6-a89e-b0b88d4d9e17","is_verified":false,"reviewed_at":null,"rejected_info":"random sad sun orange happy orange cat apple moon happy","user_id":"eb9c2609-0dc7-426b-9347-d59795d517a9","request_date":"2024-01-09T21:06:52.885Z","front_identity_card_image_link":"https://picsum.photos/200/300?random=10708346","back_identity_card_image_link":"https://picsum.photos/200/300?random=972392953","portrait_image_link":"https://picsum.photos/200/300?random=164180972","full_name":"cat sun orange cat sun sun random moon orange cat","sex":false,"dob":"2013-01-08T00:18:40.353Z","identity_card_no":"123456789187","identity_card_issued_date":"2001-07-26T21:29:58.856Z","issued_by":"Công an Hà Nội"},{"id":"ee360ff0-ff1f-4c82-a34c-1c8b4be50071","is_verified":false,"reviewed_at":null,"rejected_info":"apple dog apple cat orange orange sad banana sun orange","user_id":"346ce7ff-9c1e-43f5-8450-1296ece15692","request_date":"2024-01-09T21:06:52.885Z","front_identity_card_image_link":"https://picsum.photos/200/300?random=368951025","back_identity_card_image_link":"https://picsum.photos/200/300?random=944248786","portrait_image_link":"https://picsum.photos/200/300?random=896992122","full_name":"random orange sun cat banana cat sun sun moon cat","sex":true,"dob":"2011-01-26T16:15:12.418Z","identity_card_no":"123456789188","identity_card_issued_date":"2017-03-21T10:47:27.889Z","issued_by":"Công an Hà Nội"},{"id":"da2800f7-e9ad-404c-a8cb-5eca1a98ce52","is_verified":false,"reviewed_at":null,"rejected_info":"orange random orange sad sad orange orange apple random happy","user_id":"346ce7ff-9c1e-43f5-8450-1296ece15692","request_date":"2024-01-09T21:06:52.885Z","front_identity_card_image_link":"https://picsum.photos/200/300?random=735129355","back_identity_card_image_link":"https://picsum.photos/200/300?random=270527274","portrait_image_link":"https://picsum.photos/200/300?random=982051731","full_name":"random cat apple random banana apple random sad sad moon","sex":false,"dob":"1995-11-03T15:24:22.356Z","identity_card_no":"123456789189","identity_card_issued_date":"2023-07-04T14:22:21.362Z","issued_by":"Công an Hà Nội"},{"id":"78ab33e4-d176-428d-a12f-acdf7ac3e615","is_verified":false,"reviewed_at":null,"rejected_info":"sad banana sun dog random dog sun moon sun random","user_id":"acd91d26-4e9c-4807-94b7-57015dd554b8","request_date":"2024-01-09T21:06:52.885Z","front_identity_card_image_link":"https://picsum.photos/200/300?random=380054485","back_identity_card_image_link":"https://picsum.photos/200/300?random=71802320","portrait_image_link":"https://picsum.photos/200/300?random=795943942","full_name":"orange sad cat sad sad sad random banana dog sad","sex":false,"dob":"2002-12-30T15:03:27.007Z","identity_card_no":"123456789190","identity_card_issued_date":"2015-09-03T17:31:37.817Z","issued_by":"Công an Hà Nội"},{"id":"159b2f5b-302e-4f92-9163-ee8304e527cb","is_verified":true,"reviewed_at":"2024-01-09T21:06:52.885Z","rejected_info":null,"user_id":"891d88a3-3f3b-45d7-9bea-55398aa02b06","request_date":"2024-01-09T21:06:52.885Z","front_identity_card_image_link":"https://picsum.photos/200/300?random=227152684","back_identity_card_image_link":"https://picsum.photos/200/300?random=882929905","portrait_image_link":"https://picsum.photos/200/300?random=481729703","full_name":"dog cat happy apple moon apple cat apple random apple","sex":false,"dob":"2016-04-14T03:15:57.828Z","identity_card_no":"123456789191","identity_card_issued_date":"2002-07-05T21:21:12.818Z","issued_by":"Công an Hà Nội"},{"id":"0dc38cc3-5903-4e31-a526-c994e1b59110","is_verified":false,"reviewed_at":null,"rejected_info":"happy happy happy dog apple sad moon apple cat random","user_id":"acd91d26-4e9c-4807-94b7-57015dd554b8","request_date":"2024-01-09T21:06:52.885Z","front_identity_card_image_link":"https://picsum.photos/200/300?random=780994334","back_identity_card_image_link":"https://picsum.photos/200/300?random=116450445","portrait_image_link":"https://picsum.photos/200/300?random=529151364","full_name":"sad happy apple sun sad apple random sun cat orange","sex":false,"dob":"1981-10-07T17:58:25.251Z","identity_card_no":"123456789192","identity_card_issued_date":"2015-05-10T15:27:15.310Z","issued_by":"Công an Hà Nội"},{"id":"053821db-dbae-4950-9b59-b7150937cef9","is_verified":false,"reviewed_at":null,"rejected_info":"cat dog apple sad orange moon happy random orange dog","user_id":"032eb0aa-df19-4e4c-9b10-19ede9606f91","request_date":"2024-01-09T21:06:52.885Z","front_identity_card_image_link":"https://picsum.photos/200/300?random=298607152","back_identity_card_image_link":"https://picsum.photos/200/300?random=280200880","portrait_image_link":"https://picsum.photos/200/300?random=357521214","full_name":"sun apple dog dog cat orange moon cat sun happy","sex":false,"dob":"1977-08-21T14:31:55.874Z","identity_card_no":"123456789193","identity_card_issued_date":"2016-03-12T08:01:16.119Z","issued_by":"Công an Hà Nội"},{"id":"be464903-af78-4b2d-9700-6bce14abb1b7","is_verified":false,"reviewed_at":null,"rejected_info":"happy happy happy orange sad sun sad cat random apple","user_id":"d9f4a336-f029-4638-9815-9a0876dc159f","request_date":"2024-01-09T21:06:52.885Z","front_identity_card_image_link":"https://picsum.photos/200/300?random=592771817","back_identity_card_image_link":"https://picsum.photos/200/300?random=685311584","portrait_image_link":"https://picsum.photos/200/300?random=752059575","full_name":"orange happy orange apple happy random banana sad random happy","sex":true,"dob":"1988-05-03T13:02:15.819Z","identity_card_no":"123456789194","identity_card_issued_date":"2009-06-12T13:08:32.364Z","issued_by":"Công an Hà Nội"},{"id":"3980ddfc-a9ee-4a71-bfc7-9a7cfa442e17","is_verified":false,"reviewed_at":null,"rejected_info":"happy apple sun orange orange apple cat moon sad cat","user_id":"cda34506-be46-4dcb-94f3-e92cf8868222","request_date":"2024-01-09T21:06:52.885Z","front_identity_card_image_link":"https://picsum.photos/200/300?random=904784115","back_identity_card_image_link":"https://picsum.photos/200/300?random=505309358","portrait_image_link":"https://picsum.photos/200/300?random=171538627","full_name":"moon orange cat orange random happy sad banana happy happy","sex":false,"dob":"2015-07-31T23:08:32.417Z","identity_card_no":"123456789195","identity_card_issued_date":"2015-04-29T05:25:20.856Z","issued_by":"Công an Hà Nội"},{"id":"01b695ed-01fd-48fd-9cf9-04d5d949dae5","is_verified":false,"reviewed_at":null,"rejected_info":"happy sun happy random orange sad sad orange apple cat","user_id":"280d8b28-07ae-43e7-a54e-6468b6acf519","request_date":"2024-01-09T21:06:52.885Z","front_identity_card_image_link":"https://picsum.photos/200/300?random=192593727","back_identity_card_image_link":"https://picsum.photos/200/300?random=140137958","portrait_image_link":"https://picsum.photos/200/300?random=200632350","full_name":"banana sun banana dog apple orange dog apple sun apple","sex":false,"dob":"2001-04-26T12:24:05.200Z","identity_card_no":"123456789196","identity_card_issued_date":"2007-02-25T18:50:07.435Z","issued_by":"Công an Hà Nội"},{"id":"486b92be-bdec-410b-a1f9-e7e9a169a4e2","is_verified":false,"reviewed_at":null,"rejected_info":"moon cat random cat moon random random orange sun cat","user_id":"28223664-4747-424e-b2e3-27ace26bc553","request_date":"2024-01-09T21:06:52.885Z","front_identity_card_image_link":"https://picsum.photos/200/300?random=982707264","back_identity_card_image_link":"https://picsum.photos/200/300?random=588171485","portrait_image_link":"https://picsum.photos/200/300?random=53185985","full_name":"orange sad sun banana random happy happy orange banana apple","sex":false,"dob":"1994-09-19T02:53:42.639Z","identity_card_no":"123456789197","identity_card_issued_date":"2016-03-03T19:49:15.582Z","issued_by":"Công an Hà Nội"},{"id":"8da9fc3b-ee99-450c-8bc2-b39fdbf7cfba","is_verified":false,"reviewed_at":null,"rejected_info":"sad apple dog orange happy moon sad dog random apple","user_id":"a9eb0d7d-025b-48fa-9ff7-b792b249c159","request_date":"2024-01-09T21:06:52.885Z","front_identity_card_image_link":"https://picsum.photos/200/300?random=379540036","back_identity_card_image_link":"https://picsum.photos/200/300?random=600019688","portrait_image_link":"https://picsum.photos/200/300?random=825279972","full_name":"moon orange sun random random banana orange cat cat cat","sex":true,"dob":"1996-03-31T02:44:34.274Z","identity_card_no":"123456789198","identity_card_issued_date":"2013-12-05T10:17:03.096Z","issued_by":"Công an Hà Nội"},{"id":"9bad9c84-2a83-476a-9994-6bb122c94fe6","is_verified":false,"reviewed_at":null,"rejected_info":"random apple apple moon dog banana random cat orange moon","user_id":"acd91d26-4e9c-4807-94b7-57015dd554b8","request_date":"2024-01-09T21:06:52.885Z","front_identity_card_image_link":"https://picsum.photos/200/300?random=632721686","back_identity_card_image_link":"https://picsum.photos/200/300?random=408005402","portrait_image_link":"https://picsum.photos/200/300?random=189276812","full_name":"banana sun apple orange sun dog sad cat cat cat","sex":false,"dob":"1974-10-19T11:17:23.276Z","identity_card_no":"123456789199","identity_card_issued_date":"2006-03-01T22:49:26.994Z","issued_by":"Công an Hà Nội"},{"id":"e3e211ad-fd6c-4953-897d-bbd50d868b93","is_verified":true,"reviewed_at":"2024-01-09T21:06:52.885Z","rejected_info":null,"user_id":"5ebc825b-48dc-4b33-910d-a711999934c4","request_date":"2024-01-09T21:06:52.885Z","front_identity_card_image_link":"https://picsum.photos/200/300?random=83354442","back_identity_card_image_link":"https://picsum.photos/200/300?random=939750159","portrait_image_link":"https://picsum.photos/200/300?random=287732681","full_name":"sun cat orange random banana moon moon orange happy sad","sex":false,"dob":"1983-06-03T23:08:10.827Z","identity_card_no":"123456789200","identity_card_issued_date":"2004-07-18T02:41:09.783Z","issued_by":"Công an Hà Nội"},{"id":"301a5fc1-f6a2-4b57-ba3c-fd7eed3c20ad","is_verified":false,"reviewed_at":null,"rejected_info":"orange moon dog banana random moon orange dog apple sun","user_id":"eb9c2609-0dc7-426b-9347-d59795d517a9","request_date":"2024-01-09T21:06:52.885Z","front_identity_card_image_link":"https://picsum.photos/200/300?random=639734523","back_identity_card_image_link":"https://picsum.photos/200/300?random=646214791","portrait_image_link":"https://picsum.photos/200/300?random=966252082","full_name":"banana banana banana banana sun moon random orange moon cat","sex":false,"dob":"2007-03-04T04:57:08.775Z","identity_card_no":"123456789201","identity_card_issued_date":"2017-08-03T22:02:55.650Z","issued_by":"Công an Hà Nội"}]