[
  {
    "id": "970bbeb5-dcec-4553-a314-d1c1eadcf010",
    "reporter_id": "436660d3-98b4-45d9-98c8-098c603a442b",
    "reported_id": "d45afc3e-05e0-41a7-b38d-7e801bf92f04",
    "content_type": "inappropriate",
    "description": "happy sun cat sun sun cat sad moon random sun",
    "created_date": "2021-11-05T15:00:02.909Z",
    "status": "resolved",
    "type": "user"
  },
  {
    "id": "aa5c556c-8c43-477d-a03b-9be415bad32b",
    "reporter_id": "436660d3-98b4-45d9-98c8-098c603a442b",
    "reported_id": "b9776123-9188-4e95-995d-44311cfe7445",
    "content_type": "spam",
    "description": "happy dog sad dog moon happy apple sad sad banana",
    "created_date": "2021-12-09T18:58:03.780Z",
    "status": "resolved",
    "type": "user"
  },
  {
    "id": "661d70f5-433b-4cf2-b2b0-40eb716273e2",
    "reporter_id": "d9f4a336-f029-4638-9815-9a0876dc159f",
    "reported_id": "d45afc3e-05e0-41a7-b38d-7e801bf92f04",
    "content_type": "offensive",
    "description": "sad sad sun cat sun banana cat cat happy sun",
    "created_date": "2022-06-23T14:41:35.364Z",
    "status": "rejected",
    "type": "user"
  },
  {
    "id": "dd61ef4c-205d-407f-8a18-8a321e67c365",
    "reporter_id": "346ce7ff-9c1e-43f5-8450-1296ece15692",
    "reported_id": "3f4f6d8c-b2f1-4725-88a5-fe61ae37c8f7",
    "content_type": "inappropriate",
    "description": "happy dog orange banana sad orange random random dog apple",
    "created_date": "2021-04-06T20:48:00.026Z",
    "status": "rejected",
    "type": "post"
  },
  {
    "id": "b3e491e7-45fb-460e-9acc-eeba3522976f",
    "reporter_id": "032eb0aa-df19-4e4c-9b10-19ede9606f91",
    "reported_id": "95d29bca-2830-420c-8588-a41fe95d7a5b",
    "content_type": "other",
    "description": "dog cat happy orange happy random banana sun happy orange",
    "created_date": "2022-07-17T01:29:21.962Z",
    "status": "rejected",
    "type": "post"
  },
  {
    "id": "1696d0a7-5810-49f4-9cc5-5b26bb702603",
    "reporter_id": "a9eb0d7d-025b-48fa-9ff7-b792b249c159",
    "reported_id": "0b888fd0-9654-460d-886f-a0f185eb6682",
    "content_type": "inappropriate",
    "description": "moon moon sun orange sad random dog orange moon apple",
    "created_date": "2021-09-20T20:11:23.886Z",
    "status": "resolved",
    "type": "post"
  },
  {
    "id": "18fa7088-6b49-491c-927b-12719b4e85a7",
    "reporter_id": "8bc42aed-0036-45a2-8e1d-8041afe12d23",
    "reported_id": "8a3647ee-e418-46d5-9d0f-e85731427387",
    "content_type": "other",
    "description": "cat apple apple apple banana sun apple sad random orange",
    "created_date": "2022-11-18T23:23:54.541Z",
    "status": "rejected",
    "type": "post"
  },
  {
    "id": "5eb7dbcb-8623-47c4-acd6-777b18103ae4",
    "reporter_id": "1a9a5785-721a-4bb5-beb7-9d752e2070d4",
    "reported_id": "a9eb0d7d-025b-48fa-9ff7-b792b249c159",
    "content_type": "offensive",
    "description": "happy banana happy banana orange random sad moon happy orange",
    "created_date": "2023-11-12T08:28:54.352Z",
    "status": "pending",
    "type": "user"
  },
  {
    "id": "cca2fde2-b4d0-4a45-8765-6c6897f3390e",
    "reporter_id": "cda34506-be46-4dcb-94f3-e92cf8868222",
    "reported_id": "1a9a5785-721a-4bb5-beb7-9d752e2070d4",
    "content_type": "inappropriate",
    "description": "sun sad cat sun dog banana banana happy random moon",
    "created_date": "2022-01-26T05:14:31.333Z",
    "status": "pending",
    "type": "user"
  },
  {
    "id": "c7e447ac-59bd-42ae-bac2-f0ee8cbfd8d4",
    "reporter_id": "acd91d26-4e9c-4807-94b7-57015dd554b8",
    "reported_id": "6e740ce7-ddd8-4ecd-8de0-074aa6b45cac",
    "content_type": "inappropriate",
    "description": "dog banana cat sad orange happy banana sad sun moon",
    "created_date": "2023-02-14T06:31:20.512Z",
    "status": "rejected",
    "type": "post"
  },
  {
    "id": "8ddd6b16-957b-446b-82a1-064f1f23f21f",
    "reporter_id": "8f021f08-c21e-4d5b-8880-bd8954f37e45",
    "reported_id": "8bc42aed-0036-45a2-8e1d-8041afe12d23",
    "content_type": "other",
    "description": "random sad dog moon moon sun orange dog cat happy",
    "created_date": "2022-11-21T22:59:11.947Z",
    "status": "pending",
    "type": "user"
  },
  {
    "id": "fbea5bfb-c6cf-4e40-a3a9-9e3b8c46efab",
    "reporter_id": "8bc42aed-0036-45a2-8e1d-8041afe12d23",
    "reported_id": "d9f4a336-f029-4638-9815-9a0876dc159f",
    "content_type": "offensive",
    "description": "orange random orange apple apple dog apple apple random apple",
    "created_date": "2021-03-21T22:49:55.813Z",
    "status": "rejected",
    "type": "user"
  },
  {
    "id": "12cc75f6-47fb-475f-a685-5a3c6562bcdf",
    "reporter_id": "8bc42aed-0036-45a2-8e1d-8041afe12d23",
    "reported_id": "d45afc3e-05e0-41a7-b38d-7e801bf92f04",
    "content_type": "offensive",
    "description": "cat apple random apple apple sad happy sad cat random",
    "created_date": "2021-10-13T07:50:02.236Z",
    "status": "resolved",
    "type": "user"
  },
  {
    "id": "bc30ef5c-d36a-437a-af29-accdb504b953",
    "reporter_id": "b9776123-9188-4e95-995d-44311cfe7445",
    "reported_id": "494345a8-47a4-4d20-bd00-992d2e28f469",
    "content_type": "other",
    "description": "orange dog sad cat sad happy cat moon dog moon",
    "created_date": "2022-02-12T19:58:46.925Z",
    "status": "rejected",
    "type": "post"
  },
  {
    "id": "bc0785e5-ec6a-4f0a-9d25-09fa4a3d5b50",
    "reporter_id": "346ce7ff-9c1e-43f5-8450-1296ece15692",
    "reported_id": "acd91d26-4e9c-4807-94b7-57015dd554b8",
    "content_type": "inappropriate",
    "description": "banana banana orange sun banana dog moon happy dog banana",
    "created_date": "2022-02-18T05:12:27.292Z",
    "status": "rejected",
    "type": "user"
  },
  {
    "id": "35e67d15-5b37-4284-a8cb-6f6ad02b44e6",
    "reporter_id": "d45afc3e-05e0-41a7-b38d-7e801bf92f04",
    "reported_id": "cda34506-be46-4dcb-94f3-e92cf8868222",
    "content_type": "inappropriate",
    "description": "sad apple moon sun moon moon cat sad sun random",
    "created_date": "2021-09-25T15:37:05.481Z",
    "status": "pending",
    "type": "user"
  },
  {
    "id": "8eb60ebe-8192-4c72-9805-f65804829b76",
    "reporter_id": "8bc42aed-0036-45a2-8e1d-8041afe12d23",
    "reported_id": "6d06bb32-5ae1-46fe-b646-b42eeebdc10d",
    "content_type": "other",
    "description": "banana orange cat orange random cat cat moon apple dog",
    "created_date": "2021-01-12T23:15:22.346Z",
    "status": "rejected",
    "type": "post"
  },
  {
    "id": "70335ac0-80c3-4b83-9d29-54ab641c6893",
    "reporter_id": "280d8b28-07ae-43e7-a54e-6468b6acf519",
    "reported_id": "f0327d68-23d7-4865-a6a1-874dbeb5fc9f",
    "content_type": "other",
    "description": "cat sad moon apple dog sad moon sun sun sad",
    "created_date": "2022-11-11T18:34:14.675Z",
    "status": "pending",
    "type": "post"
  },
  {
    "id": "c2231260-51b1-4a6a-a32f-0a91da2335ce",
    "reporter_id": "cda34506-be46-4dcb-94f3-e92cf8868222",
    "reported_id": "346ce7ff-9c1e-43f5-8450-1296ece15692",
    "content_type": "spam",
    "description": "random sun random cat sad random random banana banana banana",
    "created_date": "2022-11-24T12:46:33.981Z",
    "status": "rejected",
    "type": "user"
  },
  {
    "id": "ef5ec0c6-daa1-43a9-aeac-868bfeeb3b84",
    "reporter_id": "b9776123-9188-4e95-995d-44311cfe7445",
    "reported_id": "d45afc3e-05e0-41a7-b38d-7e801bf92f04",
    "content_type": "other",
    "description": "cat random moon cat happy random random orange dog apple",
    "created_date": "2023-02-03T19:45:15.818Z",
    "status": "pending",
    "type": "user"
  },
  {
    "id": "d9b68709-6462-4dab-a9bb-65732fb87522",
    "reporter_id": "1a9a5785-721a-4bb5-beb7-9d752e2070d4",
    "reported_id": "b507105d-6d5e-4051-90e8-f5ad7d0543bf",
    "content_type": "inappropriate",
    "description": "random happy happy apple orange orange dog cat apple cat",
    "created_date": "2022-02-12T13:42:24.191Z",
    "status": "pending",
    "type": "post"
  },
  {
    "id": "aff4c255-d6bd-4006-afe8-f271285bd2d2",
    "reporter_id": "a9eb0d7d-025b-48fa-9ff7-b792b249c159",
    "reported_id": "032eb0aa-df19-4e4c-9b10-19ede9606f91",
    "content_type": "spam",
    "description": "orange cat moon sun dog dog banana moon moon banana",
    "created_date": "2023-10-09T11:42:25.501Z",
    "status": "resolved",
    "type": "user"
  },
  {
    "id": "3b5b5995-e4cc-4efe-8a7b-99a49705347e",
    "reporter_id": "346ce7ff-9c1e-43f5-8450-1296ece15692",
    "reported_id": "4366e6c4-8013-4a24-ab9c-2bc2d463a92d",
    "content_type": "spam",
    "description": "apple dog happy banana moon moon dog banana sun moon",
    "created_date": "2021-12-15T06:41:32.039Z",
    "status": "rejected",
    "type": "post"
  },
  {
    "id": "d8ebc7aa-eeea-46b4-891e-49a3f853f6dd",
    "reporter_id": "a9eb0d7d-025b-48fa-9ff7-b792b249c159",
    "reported_id": "891d88a3-3f3b-45d7-9bea-55398aa02b06",
    "content_type": "other",
    "description": "sun sad apple happy orange moon banana sun sun banana",
    "created_date": "2023-06-29T22:16:14.525Z",
    "status": "resolved",
    "type": "user"
  },
  {
    "id": "9ee5f7ab-d1ff-4eb2-ac2d-747b9159a901",
    "reporter_id": "346ce7ff-9c1e-43f5-8450-1296ece15692",
    "reported_id": "905c8998-5b9a-45eb-8fdb-6c6e30a4dd2a",
    "content_type": "offensive",
    "description": "sun cat random sad dog apple random dog orange orange",
    "created_date": "2021-05-30T13:40:33.559Z",
    "status": "pending",
    "type": "post"
  },
  {
    "id": "31c9a529-7da7-4778-88b2-7ceef79a97ee",
    "reporter_id": "436660d3-98b4-45d9-98c8-098c603a442b",
    "reported_id": "b0c08fb4-5d35-49db-91c0-db865f86e861",
    "content_type": "offensive",
    "description": "moon sad random happy happy apple sun random happy dog",
    "created_date": "2021-07-29T09:26:24.621Z",
    "status": "rejected",
    "type": "post"
  },
  {
    "id": "90d058fa-55ec-48d2-9c01-1f9d57e80954",
    "reporter_id": "5ebc825b-48dc-4b33-910d-a711999934c4",
    "reported_id": "61302423-c7bf-4329-ab86-e410a40fe6a5",
    "content_type": "inappropriate",
    "description": "sad sad random banana sad orange orange sun random random",
    "created_date": "2024-01-09T18:34:58.898Z",
    "status": "rejected",
    "type": "post"
  },
  {
    "id": "71cb4da5-bf04-4efe-9b5d-8851b955baaf",
    "reporter_id": "032eb0aa-df19-4e4c-9b10-19ede9606f91",
    "reported_id": "d32c5539-c794-4070-a735-a8880e84a425",
    "content_type": "spam",
    "description": "apple sad random happy sun cat dog happy random moon",
    "created_date": "2023-11-28T22:02:47.999Z",
    "status": "resolved",
    "type": "post"
  },
  {
    "id": "08d33bca-d904-4d8b-8be8-176c20f4409a",
    "reporter_id": "346ce7ff-9c1e-43f5-8450-1296ece15692",
    "reported_id": "898bbd17-20e4-4f86-88fe-6dc3970bcf58",
    "content_type": "other",
    "description": "dog random banana happy orange moon sad sad random happy",
    "created_date": "2023-09-23T20:55:44.241Z",
    "status": "resolved",
    "type": "post"
  },
  {
    "id": "f6c8b1de-3141-4922-af4b-28b558c1a864",
    "reporter_id": "8f021f08-c21e-4d5b-8880-bd8954f37e45",
    "reported_id": "54904e3e-b0f6-40bc-9fb6-24183e78feda",
    "content_type": "inappropriate",
    "description": "moon cat banana random moon random sun dog banana sad",
    "created_date": "2021-11-30T02:08:03.597Z",
    "status": "rejected",
    "type": "post"
  },
  {
    "id": "175b9553-f695-4064-b7b2-3458ec49c556",
    "reporter_id": "eb9c2609-0dc7-426b-9347-d59795d517a9",
    "reported_id": "d45afc3e-05e0-41a7-b38d-7e801bf92f04",
    "content_type": "other",
    "description": "happy apple dog banana cat moon moon cat banana banana",
    "created_date": "2022-06-30T04:37:00.955Z",
    "status": "resolved",
    "type": "user"
  },
  {
    "id": "d31ab843-f04b-4255-a6cc-9816ce0e8050",
    "reporter_id": "8bc42aed-0036-45a2-8e1d-8041afe12d23",
    "reported_id": "44c82dcb-d4a4-4edb-972a-889f9dd68232",
    "content_type": "spam",
    "description": "apple sun sad random random banana random sad dog apple",
    "created_date": "2022-05-21T08:48:53.577Z",
    "status": "resolved",
    "type": "post"
  },
  {
    "id": "75a51660-d622-4c51-99cb-69895b61c03c",
    "reporter_id": "8bc42aed-0036-45a2-8e1d-8041afe12d23",
    "reported_id": "b9776123-9188-4e95-995d-44311cfe7445",
    "content_type": "spam",
    "description": "cat cat happy happy sad dog dog random happy apple",
    "created_date": "2022-12-05T02:25:14.409Z",
    "status": "rejected",
    "type": "user"
  },
  {
    "id": "1c54fecd-a576-42eb-b5b6-dd1382edc968",
    "reporter_id": "d45afc3e-05e0-41a7-b38d-7e801bf92f04",
    "reported_id": "1d737b5b-4b03-45f7-8e08-ec18cc7cc3a2",
    "content_type": "spam",
    "description": "happy apple dog orange moon sun dog apple random moon",
    "created_date": "2023-06-20T21:51:10.677Z",
    "status": "pending",
    "type": "post"
  },
  {
    "id": "86cdc8e3-0d08-4b90-a6d8-7c5421e39f37",
    "reporter_id": "cda34506-be46-4dcb-94f3-e92cf8868222",
    "reported_id": "9061dc99-2a58-4a28-85e9-b6f870c7d2d5",
    "content_type": "inappropriate",
    "description": "sad sad sad cat banana cat apple dog sad orange",
    "created_date": "2021-08-25T21:38:40.491Z",
    "status": "pending",
    "type": "post"
  },
  {
    "id": "ef6596a7-2fb0-4b6a-a0ed-8defcc12e621",
    "reporter_id": "acd91d26-4e9c-4807-94b7-57015dd554b8",
    "reported_id": "28223664-4747-424e-b2e3-27ace26bc553",
    "content_type": "inappropriate",
    "description": "random dog cat dog orange happy cat orange moon banana",
    "created_date": "2023-03-02T12:15:13.178Z",
    "status": "rejected",
    "type": "user"
  },
  {
    "id": "bb5e1f99-3360-4bd1-ae75-970966037800",
    "reporter_id": "8f021f08-c21e-4d5b-8880-bd8954f37e45",
    "reported_id": "79c4b243-4cf6-4bb8-b5d0-ae7d962c4d29",
    "content_type": "other",
    "description": "dog sun happy orange sun random dog happy random moon",
    "created_date": "2022-05-21T23:55:01.764Z",
    "status": "rejected",
    "type": "post"
  },
  {
    "id": "74008c12-3e0e-4ba2-942c-7f04ab568151",
    "reporter_id": "032eb0aa-df19-4e4c-9b10-19ede9606f91",
    "reported_id": "891d88a3-3f3b-45d7-9bea-55398aa02b06",
    "content_type": "offensive",
    "description": "happy moon apple apple apple happy apple random moon random",
    "created_date": "2021-06-18T06:58:01.241Z",
    "status": "resolved",
    "type": "user"
  },
  {
    "id": "e4538c42-1ff6-4893-adfd-3b739419b0e5",
    "reporter_id": "28223664-4747-424e-b2e3-27ace26bc553",
    "reported_id": "891d88a3-3f3b-45d7-9bea-55398aa02b06",
    "content_type": "other",
    "description": "moon happy orange moon dog banana random dog sun apple",
    "created_date": "2021-11-02T06:38:45.888Z",
    "status": "resolved",
    "type": "user"
  },
  {
    "id": "7fb1089e-6224-4f45-ae4d-9f776c788bd5",
    "reporter_id": "032eb0aa-df19-4e4c-9b10-19ede9606f91",
    "reported_id": "b181908a-434b-45f3-aedd-a7457aa7b33d",
    "content_type": "inappropriate",
    "description": "cat banana apple sad apple apple cat banana sun orange",
    "created_date": "2021-02-08T07:26:59.286Z",
    "status": "rejected",
    "type": "post"
  },
  {
    "id": "9c24ab96-0ddb-4b68-b397-2b7daf200b52",
    "reporter_id": "28223664-4747-424e-b2e3-27ace26bc553",
    "reported_id": "d9f4a336-f029-4638-9815-9a0876dc159f",
    "content_type": "offensive",
    "description": "happy dog apple apple orange dog dog happy sun banana",
    "created_date": "2022-10-03T12:57:00.072Z",
    "status": "rejected",
    "type": "user"
  },
  {
    "id": "e92e8219-5b73-4418-b587-558ddd5d8b89",
    "reporter_id": "280d8b28-07ae-43e7-a54e-6468b6acf519",
    "reported_id": "9061dc99-2a58-4a28-85e9-b6f870c7d2d5",
    "content_type": "spam",
    "description": "orange cat orange happy dog orange cat apple sad sad",
    "created_date": "2022-05-23T19:52:29.389Z",
    "status": "rejected",
    "type": "post"
  },
  {
    "id": "fa5e1418-decb-4972-9336-e169aedcc8df",
    "reporter_id": "b9776123-9188-4e95-995d-44311cfe7445",
    "reported_id": "280d8b28-07ae-43e7-a54e-6468b6acf519",
    "content_type": "inappropriate",
    "description": "banana orange sun sun happy orange cat dog sad dog",
    "created_date": "2021-06-03T04:48:59.882Z",
    "status": "pending",
    "type": "user"
  },
  {
    "id": "2e39b678-0806-4d50-ac0e-8e2b54921036",
    "reporter_id": "b9776123-9188-4e95-995d-44311cfe7445",
    "reported_id": "d9f4a336-f029-4638-9815-9a0876dc159f",
    "content_type": "inappropriate",
    "description": "orange moon banana dog orange dog moon orange cat cat",
    "created_date": "2022-08-21T02:28:17.931Z",
    "status": "rejected",
    "type": "user"
  },
  {
    "id": "82c97cf8-19cf-464a-b4b2-17975b9bca61",
    "reporter_id": "b9776123-9188-4e95-995d-44311cfe7445",
    "reported_id": "acd91d26-4e9c-4807-94b7-57015dd554b8",
    "content_type": "spam",
    "description": "moon sun sad orange cat orange moon apple random banana",
    "created_date": "2022-12-04T09:05:40.200Z",
    "status": "pending",
    "type": "user"
  },
  {
    "id": "c9f36b83-272a-400c-a34e-f02a38d70315",
    "reporter_id": "032eb0aa-df19-4e4c-9b10-19ede9606f91",
    "reported_id": "6e740ce7-ddd8-4ecd-8de0-074aa6b45cac",
    "content_type": "offensive",
    "description": "moon sad cat moon random dog banana random apple random",
    "created_date": "2022-08-25T06:28:11.194Z",
    "status": "resolved",
    "type": "post"
  },
  {
    "id": "e9216fa1-99a5-42d8-b5cf-00179160304f",
    "reporter_id": "acd91d26-4e9c-4807-94b7-57015dd554b8",
    "reported_id": "8bc42aed-0036-45a2-8e1d-8041afe12d23",
    "content_type": "other",
    "description": "apple apple happy cat orange dog sad sad apple sun",
    "created_date": "2022-10-09T21:54:22.578Z",
    "status": "resolved",
    "type": "user"
  },
  {
    "id": "22825e7d-52fd-42cf-8c67-7bf8192b3b82",
    "reporter_id": "cda34506-be46-4dcb-94f3-e92cf8868222",
    "reported_id": "b9776123-9188-4e95-995d-44311cfe7445",
    "content_type": "spam",
    "description": "sad apple random random random cat cat apple banana happy",
    "created_date": "2022-01-08T17:01:01.878Z",
    "status": "pending",
    "type": "user"
  },
  {
    "id": "5aaa5cbc-66f1-45ed-a491-04cc14b3978f",
    "reporter_id": "a9eb0d7d-025b-48fa-9ff7-b792b249c159",
    "reported_id": "891d88a3-3f3b-45d7-9bea-55398aa02b06",
    "content_type": "spam",
    "description": "sad moon sad cat moon apple apple sun random happy",
    "created_date": "2022-07-30T15:45:45.713Z",
    "status": "pending",
    "type": "user"
  },
  {
    "id": "b70f0052-b6bb-4e5a-94ff-1cef17747f5b",
    "reporter_id": "d9f4a336-f029-4638-9815-9a0876dc159f",
    "reported_id": "94d7202a-2a5e-490f-bc19-1358cec5beb3",
    "content_type": "inappropriate",
    "description": "banana sad random cat orange random sad orange banana moon",
    "created_date": "2023-11-04T03:17:00.208Z",
    "status": "pending",
    "type": "post"
  },
  {
    "id": "64e38c6c-f01c-42cb-b662-c6e9671187da",
    "reporter_id": "280d8b28-07ae-43e7-a54e-6468b6acf519",
    "reported_id": "1a9a5785-721a-4bb5-beb7-9d752e2070d4",
    "content_type": "inappropriate",
    "description": "cat banana orange cat banana happy apple orange dog sun",
    "created_date": "2021-10-29T05:23:10.940Z",
    "status": "rejected",
    "type": "user"
  },
  {
    "id": "569df83f-69fc-4f74-b79c-cb2170246f86",
    "reporter_id": "d9f4a336-f029-4638-9815-9a0876dc159f",
    "reported_id": "cda34506-be46-4dcb-94f3-e92cf8868222",
    "content_type": "inappropriate",
    "description": "happy apple cat sun sun sad banana apple sad sun",
    "created_date": "2021-06-20T10:30:12.146Z",
    "status": "rejected",
    "type": "user"
  },
  {
    "id": "7318ee1b-b10a-4f89-86c1-5c52b5d4f8a4",
    "reporter_id": "1a9a5785-721a-4bb5-beb7-9d752e2070d4",
    "reported_id": "891d88a3-3f3b-45d7-9bea-55398aa02b06",
    "content_type": "inappropriate",
    "description": "sun cat moon dog random dog random moon moon random",
    "created_date": "2022-04-11T16:30:40.834Z",
    "status": "rejected",
    "type": "user"
  },
  {
    "id": "89029d94-db5a-493f-81f3-c84a4721f797",
    "reporter_id": "8bc42aed-0036-45a2-8e1d-8041afe12d23",
    "reported_id": "44c82dcb-d4a4-4edb-972a-889f9dd68232",
    "content_type": "offensive",
    "description": "cat banana orange orange random sad random sad orange random",
    "created_date": "2023-04-28T01:55:02.163Z",
    "status": "rejected",
    "type": "post"
  },
  {
    "id": "147c3053-eb10-44e9-b6cf-17bac6dee988",
    "reporter_id": "1a9a5785-721a-4bb5-beb7-9d752e2070d4",
    "reported_id": "6e740ce7-ddd8-4ecd-8de0-074aa6b45cac",
    "content_type": "offensive",
    "description": "happy banana sun moon random apple happy sun orange banana",
    "created_date": "2021-05-27T07:04:23.032Z",
    "status": "rejected",
    "type": "post"
  },
  {
    "id": "d8c5d982-5971-469a-83c9-5e0905e5c0e8",
    "reporter_id": "5ebc825b-48dc-4b33-910d-a711999934c4",
    "reported_id": "61302423-c7bf-4329-ab86-e410a40fe6a5",
    "content_type": "inappropriate",
    "description": "dog happy cat orange banana random moon sad moon happy",
    "created_date": "2023-07-13T06:45:35.023Z",
    "status": "rejected",
    "type": "post"
  },
  {
    "id": "5e9edc29-6a8d-48ad-b441-65efcebb09a8",
    "reporter_id": "891d88a3-3f3b-45d7-9bea-55398aa02b06",
    "reported_id": "9eb3dc8a-0861-400d-8f76-242e7bfa625b",
    "content_type": "other",
    "description": "apple sad happy apple sun sad sun happy apple orange",
    "created_date": "2023-07-28T18:27:27.340Z",
    "status": "pending",
    "type": "post"
  },
  {
    "id": "23e84a75-97de-4409-9229-2512db429d4b",
    "reporter_id": "5ebc825b-48dc-4b33-910d-a711999934c4",
    "reported_id": "0b888fd0-9654-460d-886f-a0f185eb6682",
    "content_type": "inappropriate",
    "description": "happy happy sun sun dog moon banana dog banana orange",
    "created_date": "2023-01-21T19:48:34.289Z",
    "status": "resolved",
    "type": "post"
  },
  {
    "id": "71e05714-3618-4fcc-805f-c9d08efe05db",
    "reporter_id": "cda34506-be46-4dcb-94f3-e92cf8868222",
    "reported_id": "280d8b28-07ae-43e7-a54e-6468b6acf519",
    "content_type": "inappropriate",
    "description": "random random orange random apple sun cat cat orange random",
    "created_date": "2023-02-22T19:22:08.180Z",
    "status": "pending",
    "type": "user"
  },
  {
    "id": "e5cf9810-3aa9-46f3-b82c-2f3551448165",
    "reporter_id": "5ebc825b-48dc-4b33-910d-a711999934c4",
    "reported_id": "f22d6152-3abd-4da9-9032-c3fea49414dd",
    "content_type": "other",
    "description": "banana sun orange random orange sun apple happy happy random",
    "created_date": "2021-07-04T13:18:51.580Z",
    "status": "rejected",
    "type": "post"
  },
  {
    "id": "5a9c2e17-313c-47ab-8f61-1d8e001a1da4",
    "reporter_id": "eb9c2609-0dc7-426b-9347-d59795d517a9",
    "reported_id": "a9eb0d7d-025b-48fa-9ff7-b792b249c159",
    "content_type": "offensive",
    "description": "dog dog dog orange banana moon banana random moon sad",
    "created_date": "2021-10-10T20:52:02.815Z",
    "status": "rejected",
    "type": "user"
  },
  {
    "id": "d0cd624f-cb3d-4e41-a11d-42697e71d34d",
    "reporter_id": "cda34506-be46-4dcb-94f3-e92cf8868222",
    "reported_id": "ecdd6009-cc4e-4b97-add4-e996b2aded0f",
    "content_type": "spam",
    "description": "cat happy sad sun dog random random orange apple random",
    "created_date": "2023-01-05T21:48:35.864Z",
    "status": "pending",
    "type": "post"
  },
  {
    "id": "dcfd9214-d93d-40ff-969c-ec4b7c3a7646",
    "reporter_id": "eb9c2609-0dc7-426b-9347-d59795d517a9",
    "reported_id": "cac98a37-ea4f-45df-b88f-d59a4ad963fc",
    "content_type": "spam",
    "description": "sun cat happy sun sun happy cat happy banana apple",
    "created_date": "2023-07-02T03:15:22.272Z",
    "status": "resolved",
    "type": "post"
  },
  {
    "id": "a6a891fa-7cf6-4e1f-9f58-2e1c3a4ffb76",
    "reporter_id": "b9776123-9188-4e95-995d-44311cfe7445",
    "reported_id": "4eef1903-93d0-4654-8d19-45ec4e13434f",
    "content_type": "inappropriate",
    "description": "happy banana cat sun moon apple banana orange sad sad",
    "created_date": "2021-11-13T07:07:32.748Z",
    "status": "resolved",
    "type": "post"
  },
  {
    "id": "6d5b2d1d-a07c-4203-b6ba-8ba2d07053ec",
    "reporter_id": "8bc42aed-0036-45a2-8e1d-8041afe12d23",
    "reported_id": "c3f52b42-79d7-4fc7-9035-690573685139",
    "content_type": "offensive",
    "description": "happy random cat sad moon dog sun sad sad sun",
    "created_date": "2022-09-10T01:38:40.785Z",
    "status": "rejected",
    "type": "post"
  },
  {
    "id": "81b05d9f-e848-4fb6-a922-e0cbd417bd37",
    "reporter_id": "1a9a5785-721a-4bb5-beb7-9d752e2070d4",
    "reported_id": "3f4f6d8c-b2f1-4725-88a5-fe61ae37c8f7",
    "content_type": "other",
    "description": "cat happy sad cat moon orange happy dog cat sad",
    "created_date": "2023-01-28T16:40:18.442Z",
    "status": "resolved",
    "type": "post"
  },
  {
    "id": "527dd3a8-ff6f-465d-be5b-136a9181bf11",
    "reporter_id": "b9776123-9188-4e95-995d-44311cfe7445",
    "reported_id": "a5132ef2-ef12-4d7d-985f-119c615c3bb1",
    "content_type": "inappropriate",
    "description": "orange cat cat apple orange moon orange orange sun banana",
    "created_date": "2022-08-05T22:45:19.983Z",
    "status": "rejected",
    "type": "post"
  },
  {
    "id": "21e96a09-4997-432d-99fe-92ce2edeab90",
    "reporter_id": "032eb0aa-df19-4e4c-9b10-19ede9606f91",
    "reported_id": "80998a46-70a5-407c-9dd9-0c220a143852",
    "content_type": "spam",
    "description": "apple random cat banana apple random sun banana sun dog",
    "created_date": "2021-07-14T06:48:01.007Z",
    "status": "rejected",
    "type": "post"
  },
  {
    "id": "9482bf66-e512-4c50-8fd5-d3104ee05286",
    "reporter_id": "5ebc825b-48dc-4b33-910d-a711999934c4",
    "reported_id": "94d7202a-2a5e-490f-bc19-1358cec5beb3",
    "content_type": "inappropriate",
    "description": "sun cat banana happy sad moon banana orange orange moon",
    "created_date": "2021-06-11T10:52:50.284Z",
    "status": "resolved",
    "type": "post"
  },
  {
    "id": "4826e498-21ea-4b3c-bb00-496cc0331ec0",
    "reporter_id": "eb9c2609-0dc7-426b-9347-d59795d517a9",
    "reported_id": "1a9a5785-721a-4bb5-beb7-9d752e2070d4",
    "content_type": "spam",
    "description": "apple cat cat apple random apple moon cat orange moon",
    "created_date": "2021-01-06T05:26:05.195Z",
    "status": "pending",
    "type": "user"
  },
  {
    "id": "84ba0aca-8ddc-4bca-87af-801444efab39",
    "reporter_id": "28223664-4747-424e-b2e3-27ace26bc553",
    "reported_id": "891d88a3-3f3b-45d7-9bea-55398aa02b06",
    "content_type": "other",
    "description": "cat moon moon happy random cat cat apple dog dog",
    "created_date": "2021-04-10T22:27:46.573Z",
    "status": "rejected",
    "type": "user"
  },
  {
    "id": "de5eb070-ef6e-4d17-84c1-56cd1f88b574",
    "reporter_id": "d45afc3e-05e0-41a7-b38d-7e801bf92f04",
    "reported_id": "4d8914ac-a5e0-4195-835f-41568f58e737",
    "content_type": "inappropriate",
    "description": "sad random random orange random apple moon orange moon orange",
    "created_date": "2023-08-28T01:34:55.499Z",
    "status": "rejected",
    "type": "post"
  },
  {
    "id": "9a63e241-10c9-4aa9-af8e-4078ecac6fc4",
    "reporter_id": "436660d3-98b4-45d9-98c8-098c603a442b",
    "reported_id": "082f9c09-8050-49e6-b22d-0f6eb3becd93",
    "content_type": "other",
    "description": "moon banana orange cat sun cat moon banana orange random",
    "created_date": "2021-03-13T20:05:42.555Z",
    "status": "resolved",
    "type": "post"
  },
  {
    "id": "2942a4c8-bc6e-449d-9dd7-60678c67a500",
    "reporter_id": "346ce7ff-9c1e-43f5-8450-1296ece15692",
    "reported_id": "5c8ab152-943f-47d2-87d6-9a7568ce21a5",
    "content_type": "inappropriate",
    "description": "banana happy dog sad moon cat sun banana moon sun",
    "created_date": "2022-03-12T19:19:19.034Z",
    "status": "pending",
    "type": "post"
  },
  {
    "id": "24c9183d-bcc5-43ae-82a6-46a1aab76072",
    "reporter_id": "1a9a5785-721a-4bb5-beb7-9d752e2070d4",
    "reported_id": "891d88a3-3f3b-45d7-9bea-55398aa02b06",
    "content_type": "offensive",
    "description": "orange sun apple moon sun orange orange orange dog random",
    "created_date": "2022-04-26T12:43:16.455Z",
    "status": "resolved",
    "type": "user"
  },
  {
    "id": "f4bcc481-f7a3-4d6c-8cde-ec1ee955b223",
    "reporter_id": "891d88a3-3f3b-45d7-9bea-55398aa02b06",
    "reported_id": "a9eb0d7d-025b-48fa-9ff7-b792b249c159",
    "content_type": "other",
    "description": "sad happy sad moon sun sad random random sun orange",
    "created_date": "2022-05-23T19:33:46.027Z",
    "status": "resolved",
    "type": "user"
  },
  {
    "id": "28c5ac6c-6dcb-47a2-b652-0bb0a8eda520",
    "reporter_id": "8f021f08-c21e-4d5b-8880-bd8954f37e45",
    "reported_id": "760eb771-ea68-4956-910f-684c5c196980",
    "content_type": "spam",
    "description": "sun sad dog dog dog banana moon banana dog orange",
    "created_date": "2023-10-16T19:27:15.225Z",
    "status": "pending",
    "type": "post"
  },
  {
    "id": "c6ec214d-93e0-4749-89f3-29b4a15699ec",
    "reporter_id": "eb9c2609-0dc7-426b-9347-d59795d517a9",
    "reported_id": "80998a46-70a5-407c-9dd9-0c220a143852",
    "content_type": "inappropriate",
    "description": "sad random banana sad moon banana orange sad dog random",
    "created_date": "2022-12-19T18:49:46.779Z",
    "status": "rejected",
    "type": "post"
  },
  {
    "id": "a9ac5775-71d5-4e3f-95e4-7d78028dd590",
    "reporter_id": "346ce7ff-9c1e-43f5-8450-1296ece15692",
    "reported_id": "acd91d26-4e9c-4807-94b7-57015dd554b8",
    "content_type": "offensive",
    "description": "apple cat orange apple sun random orange orange banana dog",
    "created_date": "2022-09-29T02:57:26.427Z",
    "status": "resolved",
    "type": "user"
  },
  {
    "id": "0f434e5d-7e3f-4ea5-a93c-3258cd1f31c9",
    "reporter_id": "28223664-4747-424e-b2e3-27ace26bc553",
    "reported_id": "891d88a3-3f3b-45d7-9bea-55398aa02b06",
    "content_type": "inappropriate",
    "description": "happy orange happy banana sun happy sun happy banana orange",
    "created_date": "2023-05-08T19:43:33.170Z",
    "status": "resolved",
    "type": "user"
  },
  {
    "id": "c23f5c21-7f84-464e-b735-bb71443d1c34",
    "reporter_id": "a9eb0d7d-025b-48fa-9ff7-b792b249c159",
    "reported_id": "032eb0aa-df19-4e4c-9b10-19ede9606f91",
    "content_type": "spam",
    "description": "cat orange happy dog cat orange happy moon random banana",
    "created_date": "2021-03-03T22:52:14.205Z",
    "status": "resolved",
    "type": "user"
  },
  {
    "id": "eb932790-56b7-4075-a6b9-13611eca1ed4",
    "reporter_id": "acd91d26-4e9c-4807-94b7-57015dd554b8",
    "reported_id": "760eb771-ea68-4956-910f-684c5c196980",
    "content_type": "spam",
    "description": "random sad moon dog moon dog sun sun dog happy",
    "created_date": "2022-10-12T17:17:01.730Z",
    "status": "resolved",
    "type": "post"
  },
  {
    "id": "5186a711-4165-40d1-ba63-f0840536e103",
    "reporter_id": "acd91d26-4e9c-4807-94b7-57015dd554b8",
    "reported_id": "a9eb0d7d-025b-48fa-9ff7-b792b249c159",
    "content_type": "offensive",
    "description": "dog sad dog cat apple random random sad happy apple",
    "created_date": "2023-07-19T05:47:46.201Z",
    "status": "pending",
    "type": "user"
  },
  {
    "id": "a0700cbc-1b7a-47ce-bf22-e23bdaa8b990",
    "reporter_id": "a9eb0d7d-025b-48fa-9ff7-b792b249c159",
    "reported_id": "94d7202a-2a5e-490f-bc19-1358cec5beb3",
    "content_type": "inappropriate",
    "description": "random sun banana banana happy happy banana apple orange dog",
    "created_date": "2022-04-25T04:28:02.515Z",
    "status": "resolved",
    "type": "post"
  },
  {
    "id": "9c82c413-4a1c-4b25-855b-a7d11d7b3e37",
    "reporter_id": "28223664-4747-424e-b2e3-27ace26bc553",
    "reported_id": "1af55db9-87da-4dc1-8921-aebe8422b800",
    "content_type": "offensive",
    "description": "cat cat moon banana happy sun orange sun random random",
    "created_date": "2023-09-17T23:20:03.135Z",
    "status": "pending",
    "type": "post"
  },
  {
    "id": "475f465f-a16b-4e65-9dcb-e4cb35bd0d66",
    "reporter_id": "a9eb0d7d-025b-48fa-9ff7-b792b249c159",
    "reported_id": "436660d3-98b4-45d9-98c8-098c603a442b",
    "content_type": "inappropriate",
    "description": "sad cat cat happy sun happy sad happy banana apple",
    "created_date": "2022-06-24T19:11:52.970Z",
    "status": "rejected",
    "type": "user"
  },
  {
    "id": "a32d50cf-90a4-40c0-9ab1-3541cdc89e65",
    "reporter_id": "b9776123-9188-4e95-995d-44311cfe7445",
    "reported_id": "032eb0aa-df19-4e4c-9b10-19ede9606f91",
    "content_type": "offensive",
    "description": "dog sad apple happy banana moon sad sad sun orange",
    "created_date": "2021-08-08T07:58:13.450Z",
    "status": "rejected",
    "type": "user"
  },
  {
    "id": "2bddc98d-616e-4ad1-8ab5-bc1f826a0c0a",
    "reporter_id": "cda34506-be46-4dcb-94f3-e92cf8868222",
    "reported_id": "88f3fbe7-2511-4e95-9bf4-d14ac1705845",
    "content_type": "offensive",
    "description": "dog sad moon cat dog happy cat moon cat cat",
    "created_date": "2023-10-18T11:17:05.611Z",
    "status": "resolved",
    "type": "post"
  },
  {
    "id": "ce5a115d-6220-41b1-a734-62d4c433fcf8",
    "reporter_id": "5ebc825b-48dc-4b33-910d-a711999934c4",
    "reported_id": "c44cbad4-ad93-4cb1-810b-b6680bf8f8db",
    "content_type": "offensive",
    "description": "dog banana sad orange sun cat random dog sad orange",
    "created_date": "2023-10-01T11:11:13.622Z",
    "status": "pending",
    "type": "post"
  },
  {
    "id": "9de6ded5-1ca9-44df-96fc-93fb7a64a012",
    "reporter_id": "280d8b28-07ae-43e7-a54e-6468b6acf519",
    "reported_id": "74540a0b-1c39-4eb0-b5ad-eb02e0c822d2",
    "content_type": "inappropriate",
    "description": "sun orange orange orange random random sun random sad orange",
    "created_date": "2022-06-17T17:14:20.102Z",
    "status": "pending",
    "type": "post"
  },
  {
    "id": "056ecd6d-5f22-4a02-a1fc-1679bee5a587",
    "reporter_id": "d45afc3e-05e0-41a7-b38d-7e801bf92f04",
    "reported_id": "5a560d98-3508-46e7-aa6b-57405b2fcbaa",
    "content_type": "other",
    "description": "apple moon random apple sun dog banana apple cat sad",
    "created_date": "2022-11-11T07:43:21.425Z",
    "status": "rejected",
    "type": "post"
  },
  {
    "id": "55722154-83ad-40e8-9e3e-e6a4193fc613",
    "reporter_id": "acd91d26-4e9c-4807-94b7-57015dd554b8",
    "reported_id": "28223664-4747-424e-b2e3-27ace26bc553",
    "content_type": "spam",
    "description": "random moon happy sad dog random apple random happy happy",
    "created_date": "2021-09-15T01:52:34.020Z",
    "status": "resolved",
    "type": "user"
  },
  {
    "id": "cacb027b-0fc8-40c0-afc2-fcfe51a48967",
    "reporter_id": "8bc42aed-0036-45a2-8e1d-8041afe12d23",
    "reported_id": "4366e6c4-8013-4a24-ab9c-2bc2d463a92d",
    "content_type": "offensive",
    "description": "dog sun apple orange cat sad cat cat dog banana",
    "created_date": "2022-07-13T08:43:48.350Z",
    "status": "resolved",
    "type": "post"
  },
  {
    "id": "09c6b679-9db8-4a39-8f85-af67576baec6",
    "reporter_id": "cda34506-be46-4dcb-94f3-e92cf8868222",
    "reported_id": "28223664-4747-424e-b2e3-27ace26bc553",
    "content_type": "other",
    "description": "cat sad happy apple banana banana cat cat sun sad",
    "created_date": "2022-12-27T01:47:51.387Z",
    "status": "pending",
    "type": "user"
  },
  {
    "id": "a06fd14b-c761-4f6a-a158-5fd3d8a3c6e3",
    "reporter_id": "d45afc3e-05e0-41a7-b38d-7e801bf92f04",
    "reported_id": "b5465b1d-3fb2-46b9-a745-42826cc3ec9b",
    "content_type": "offensive",
    "description": "random apple sun orange happy banana sun apple cat apple",
    "created_date": "2021-03-27T08:43:35.945Z",
    "status": "resolved",
    "type": "post"
  },
  {
    "id": "bba442f7-9bef-4eda-a624-32a0acc14290",
    "reporter_id": "eb9c2609-0dc7-426b-9347-d59795d517a9",
    "reported_id": "1d737b5b-4b03-45f7-8e08-ec18cc7cc3a2",
    "content_type": "offensive",
    "description": "random orange moon cat sad dog banana cat moon sun",
    "created_date": "2022-03-26T11:07:24.433Z",
    "status": "pending",
    "type": "post"
  },
  {
    "id": "d81dff46-cd05-4cfd-aa9b-cdb58bc1c11f",
    "reporter_id": "280d8b28-07ae-43e7-a54e-6468b6acf519",
    "reported_id": "032eb0aa-df19-4e4c-9b10-19ede9606f91",
    "content_type": "spam",
    "description": "sad dog sad banana random apple orange apple sad sad",
    "created_date": "2023-01-31T12:08:23.033Z",
    "status": "pending",
    "type": "user"
  },
  {
    "id": "c4734579-461b-4644-bfd0-0c7b5aa548ca",
    "reporter_id": "280d8b28-07ae-43e7-a54e-6468b6acf519",
    "reported_id": "acd91d26-4e9c-4807-94b7-57015dd554b8",
    "content_type": "offensive",
    "description": "happy happy happy happy apple random sad orange happy dog",
    "created_date": "2022-07-20T12:03:31.065Z",
    "status": "rejected",
    "type": "user"
  },
  {
    "id": "1980ec69-4ce0-4115-a678-eff0dd1c149f",
    "reporter_id": "d45afc3e-05e0-41a7-b38d-7e801bf92f04",
    "reported_id": "5ebc825b-48dc-4b33-910d-a711999934c4",
    "content_type": "inappropriate",
    "description": "apple cat apple banana happy orange happy happy orange sad",
    "created_date": "2021-01-28T10:53:35.830Z",
    "status": "rejected",
    "type": "user"
  },
  {
    "id": "75dd9a19-50f5-4135-b87b-2f89060af82c",
    "reporter_id": "a9eb0d7d-025b-48fa-9ff7-b792b249c159",
    "reported_id": "5ebc825b-48dc-4b33-910d-a711999934c4",
    "content_type": "spam",
    "description": "sad happy orange apple sad random happy moon moon sun",
    "created_date": "2021-07-30T15:23:23.149Z",
    "status": "pending",
    "type": "user"
  }
]